{
  "type" : "FeatureCollection",
  "features" : [{"type":"Feature","id":0,"geometry":{"type":"Point","coordinates":[197900,198620]},"properties":{"FID":0,"PMD_CODE":"AC/020","PMD_X":197900,"PMD_Y":198620,"PMD_Z":-160,"PN_NAME_E":"Baidah","GR_GOVERNA":"Tubas","LOC_NAME_E":"'Ein el Beida","PT_POINT_T":"Spring"}},{"type":"Feature","id":1,"geometry":{"type":"Point","coordinates":[199180,199280]},"properties":{"FID":1,"PMD_CODE":"AC/021","PMD_X":199180,"PMD_Y":199280,"PMD_Z":-200,"PN_NAME_E":"Al Deir","GR_GOVERNA":"Tubas","LOC_NAME_E":"'Ein el Beida","PT_POINT_T":"Spring"}},{"type":"Feature","id":2,"geometry":{"type":"Point","coordinates":[199200,199300]},"properties":{"FID":2,"PMD_CODE":"AC/022","PMD_X":199200,"PMD_Y":199300,"PMD_Z":-180,"PN_NAME_E":"Al Qur'an","GR_GOVERNA":"Tubas","LOC_NAME_E":"'Ein el Beida","PT_POINT_T":"Spring"}},{"type":"Feature","id":3,"geometry":{"type":"Point","coordinates":[198400,198420]},"properties":{"FID":3,"PMD_CODE":"AC/023","PMD_X":198400,"PMD_Y":198420,"PMD_Z":-180,"PN_NAME_E":"Al Shamsiyyah Al Tehta","GR_GOVERNA":"Tubas","LOC_NAME_E":"'Ein el Beida","PT_POINT_T":"Spring"}},{"type":"Feature","id":4,"geometry":{"type":"Point","coordinates":[197600,198400]},"properties":{"FID":4,"PMD_CODE":"AC/024","PMD_X":197600,"PMD_Y":198400,"PMD_Z":-160,"PN_NAME_E":"Al Shamsiyyah Al Fuqa","GR_GOVERNA":"Tubas","LOC_NAME_E":"'Ein el Beida","PT_POINT_T":"Spring"}},{"type":"Feature","id":5,"geometry":{"type":"Point","coordinates":[198130,198770]},"properties":{"FID":5,"PMD_CODE":"AC/025","PMD_X":198130,"PMD_Y":198770,"PMD_Z":-175,"PN_NAME_E":"Al Munhadariyyat Al Fuqa","GR_GOVERNA":"Tubas","LOC_NAME_E":"'Ein el Beida","PT_POINT_T":"Spring"}},{"type":"Feature","id":6,"geometry":{"type":"Point","coordinates":[198230,198770]},"properties":{"FID":6,"PMD_CODE":"AC/025A","PMD_X":198230,"PMD_Y":198770,"PMD_Z":-175,"PN_NAME_E":"Al Munhadariyyat Al Tehta","GR_GOVERNA":"Tubas","LOC_NAME_E":"'Ein el Beida","PT_POINT_T":"Spring"}},{"type":"Feature","id":7,"geometry":{"type":"Point","coordinates":[199400,199870]},"properties":{"FID":7,"PMD_CODE":"AC/026","PMD_X":199400,"PMD_Y":199870,"PMD_Z":-200,"PN_NAME_E":"Al Fatur","GR_GOVERNA":"Tubas","LOC_NAME_E":"'Ein el Beida","PT_POINT_T":"Spring"}},{"type":"Feature","id":8,"geometry":{"type":"Point","coordinates":[199100,200000]},"properties":{"FID":8,"PMD_CODE":"AC/027","PMD_X":199100,"PMD_Y":200000,"PMD_Z":-205,"PN_NAME_E":"Abu Afeef","GR_GOVERNA":"Tubas","LOC_NAME_E":"'Ein el Beida","PT_POINT_T":"Spring"}},{"type":"Feature","id":9,"geometry":{"type":"Point","coordinates":[198300,198900]},"properties":{"FID":9,"PMD_CODE":"AC/028","PMD_X":198300,"PMD_Y":198900,"PMD_Z":-180,"PN_NAME_E":"Ed Dibis","GR_GOVERNA":"Tubas","LOC_NAME_E":"'Ein el Beida","PT_POINT_T":"Spring"}},{"type":"Feature","id":10,"geometry":{"type":"Point","coordinates":[202000,198100]},"properties":{"FID":10,"PMD_CODE":"AC/029","PMD_X":202000,"PMD_Y":198100,"PMD_Z":-260,"PN_NAME_E":"Frata","GR_GOVERNA":"Tubas","LOC_NAME_E":"Bardala","PT_POINT_T":"Spring"}},{"type":"Feature","id":11,"geometry":{"type":"Point","coordinates":[197200,197560]},"properties":{"FID":11,"PMD_CODE":"AC/030A","PMD_X":197200,"PMD_Y":197560,"PMD_Z":-100,"PN_NAME_E":"Al Himmah Al Fuqa","GR_GOVERNA":"Tubas","LOC_NAME_E":"Bardala","PT_POINT_T":"Spring"}},{"type":"Feature","id":12,"geometry":{"type":"Point","coordinates":[197300,196800]},"properties":{"FID":12,"PMD_CODE":"AC/030B","PMD_X":197300,"PMD_Y":196800,"PMD_Z":-100,"PN_NAME_E":"Al Himmah Al Tehta","GR_GOVERNA":"Tubas","LOC_NAME_E":"Bardala","PT_POINT_T":"Spring"}},{"type":"Feature","id":13,"geometry":{"type":"Point","coordinates":[196200,198260]},"properties":{"FID":13,"PMD_CODE":"AC/031","PMD_X":196200,"PMD_Y":198260,"PMD_Z":0,"PN_NAME_E":"Kardala","GR_GOVERNA":"Tubas","LOC_NAME_E":"Bardala","PT_POINT_T":"Spring"}},{"type":"Feature","id":14,"geometry":{"type":"Point","coordinates":[195220,199280]},"properties":{"FID":14,"PMD_CODE":"AC/032","PMD_X":195220,"PMD_Y":199280,"PMD_Z":0,"PN_NAME_E":"Bardala","GR_GOVERNA":"Tubas","LOC_NAME_E":"Bardala","PT_POINT_T":"Spring"}},{"type":"Feature","id":15,"geometry":{"type":"Point","coordinates":[195430,199430]},"properties":{"FID":15,"PMD_CODE":"AC/032A","PMD_X":195430,"PMD_Y":199430,"PMD_Z":0,"PN_NAME_E":"El 'Arak","GR_GOVERNA":"Tubas","LOC_NAME_E":"Bardala","PT_POINT_T":"Spring"}},{"type":"Feature","id":16,"geometry":{"type":"Point","coordinates":[194200,201400]},"properties":{"FID":16,"PMD_CODE":"AC/033","PMD_X":194200,"PMD_Y":201400,"PMD_Z":-60,"PN_NAME_E":"Qa'un","GR_GOVERNA":"Tubas","LOC_NAME_E":"Bardala","PT_POINT_T":"Spring"}},{"type":"Feature","id":17,"geometry":{"type":"Point","coordinates":[202100,197800]},"properties":{"FID":17,"PMD_CODE":"AC/034","PMD_X":202100,"PMD_Y":197800,"PMD_Z":-260,"PN_NAME_E":"El Sufsafe","GR_GOVERNA":"Tubas","LOC_NAME_E":"Bardala","PT_POINT_T":"Spring"}},{"type":"Feature","id":18,"geometry":{"type":"Point","coordinates":[199860,199660]},"properties":{"FID":18,"PMD_CODE":"AC/035","PMD_X":199860,"PMD_Y":199660,"PMD_Z":-190,"PN_NAME_E":"Blaibel","GR_GOVERNA":"Tubas","LOC_NAME_E":"Bardala","PT_POINT_T":"Spring"}},{"type":"Feature","id":19,"geometry":{"type":"Point","coordinates":[199800,200000]},"properties":{"FID":19,"PMD_CODE":"AC/036","PMD_X":199800,"PMD_Y":200000,"PMD_Z":0,"PN_NAME_E":"Hasan Al Shuha","GR_GOVERNA":"Tubas","LOC_NAME_E":"Bardala","PT_POINT_T":"Spring"}},{"type":"Feature","id":20,"geometry":{"type":"Point","coordinates":[201800,196800]},"properties":{"FID":20,"PMD_CODE":"AC/037","PMD_X":201800,"PMD_Y":196800,"PMD_Z":-225,"PN_NAME_E":"Al Saqut","GR_GOVERNA":"Tubas","LOC_NAME_E":"Sacut","PT_POINT_T":"Spring"}},{"type":"Feature","id":21,"geometry":{"type":"Point","coordinates":[197800,197500]},"properties":{"FID":21,"PMD_CODE":"AC/040","PMD_X":197800,"PMD_Y":197500,"PMD_Z":-100,"PN_NAME_E":"Al Hulwah","GR_GOVERNA":"Tubas","LOC_NAME_E":"Bardala","PT_POINT_T":"Spring"}},{"type":"Feature","id":22,"geometry":{"type":"Point","coordinates":[195000,192620]},"properties":{"FID":22,"PMD_CODE":"AC/041","PMD_X":195000,"PMD_Y":192620,"PMD_Z":-12,"PN_NAME_E":"Hammam Al Maleh","GR_GOVERNA":"Tubas","LOC_NAME_E":"Bardala","PT_POINT_T":"Spring"}},{"type":"Feature","id":23,"geometry":{"type":"Point","coordinates":[187900,173600]},"properties":{"FID":23,"PMD_CODE":"AC/050","PMD_X":187900,"PMD_Y":173600,"PMD_Z":300,"PN_NAME_E":"Tana 1+2","GR_GOVERNA":"Nablus","LOC_NAME_E":"Beit Furik","PT_POINT_T":"Spring"}},{"type":"Feature","id":24,"geometry":{"type":"Point","coordinates":[187600,175900]},"properties":{"FID":24,"PMD_CODE":"AC/051","PMD_X":187600,"PMD_Y":175900,"PMD_Z":410,"PN_NAME_E":"Sh'ab Al Beer","GR_GOVERNA":"Nablus","LOC_NAME_E":"Beit Furik","PT_POINT_T":"Spring"}},{"type":"Feature","id":25,"geometry":{"type":"Point","coordinates":[185500,171400]},"properties":{"FID":25,"PMD_CODE":"AC/052","PMD_X":185500,"PMD_Y":171400,"PMD_Z":395,"PN_NAME_E":"Al Dawwa","GR_GOVERNA":"Nablus","LOC_NAME_E":"Aqraba","PT_POINT_T":"Spring"}},{"type":"Feature","id":26,"geometry":{"type":"Point","coordinates":[185300,171000]},"properties":{"FID":26,"PMD_CODE":"AC/053","PMD_X":185300,"PMD_Y":171000,"PMD_Z":365,"PN_NAME_E":"Al Jaheer","GR_GOVERNA":"Nablus","LOC_NAME_E":"Aqraba","PT_POINT_T":"Spring"}},{"type":"Feature","id":27,"geometry":{"type":"Point","coordinates":[188300,162000]},"properties":{"FID":27,"PMD_CODE":"AC/054","PMD_X":188300,"PMD_Y":162000,"PMD_Z":-110,"PN_NAME_E":"Fasayil","GR_GOVERNA":"Jericho","LOC_NAME_E":"Al Jiftlik","PT_POINT_T":"Spring"}},{"type":"Feature","id":28,"geometry":{"type":"Point","coordinates":[190050,144660]},"properties":{"FID":28,"PMD_CODE":"AC/060","PMD_X":190050,"PMD_Y":144660,"PMD_Z":-115,"PN_NAME_E":"Al Dyuk","GR_GOVERNA":"Jericho","LOC_NAME_E":"Jericho (Ariha)","PT_POINT_T":"Spring"}},{"type":"Feature","id":29,"geometry":{"type":"Point","coordinates":[190040,144720]},"properties":{"FID":29,"PMD_CODE":"AC/060A","PMD_X":190040,"PMD_Y":144720,"PMD_Z":-110,"PN_NAME_E":"Al Nwai'mah","GR_GOVERNA":"Jericho","LOC_NAME_E":"Jericho (Ariha)","PT_POINT_T":"Spring"}},{"type":"Feature","id":30,"geometry":{"type":"Point","coordinates":[190000,144800]},"properties":{"FID":30,"PMD_CODE":"AC/060B","PMD_X":190000,"PMD_Y":144800,"PMD_Z":-110,"PN_NAME_E":"Al Shusah","GR_GOVERNA":"Jericho","LOC_NAME_E":"Jericho (Ariha)","PT_POINT_T":"Spring"}},{"type":"Feature","id":31,"geometry":{"type":"Point","coordinates":[192200,141950]},"properties":{"FID":31,"PMD_CODE":"AC/061","PMD_X":192200,"PMD_Y":141950,"PMD_Z":-215,"PN_NAME_E":"Al Sultan","GR_GOVERNA":"Jericho","LOC_NAME_E":"Jericho (Ariha)","PT_POINT_T":"Spring"}},{"type":"Feature","id":32,"geometry":{"type":"Point","coordinates":[198700,170900]},"properties":{"FID":32,"PMD_CODE":"AQ/020","PMD_X":198700,"PMD_Y":170900,"PMD_Z":280,"PN_NAME_E":"Bassat Mahrug","GR_GOVERNA":"Jericho","LOC_NAME_E":"Al Jiftlik","PT_POINT_T":"Spring"}},{"type":"Feature","id":33,"geometry":{"type":"Point","coordinates":[199200,169000]},"properties":{"FID":33,"PMD_CODE":"AQ/021","PMD_X":199200,"PMD_Y":169000,"PMD_Z":290,"PN_NAME_E":"Josala","GR_GOVERNA":"Jericho","LOC_NAME_E":"Al Jiftlik","PT_POINT_T":"Spring"}},{"type":"Feature","id":34,"geometry":{"type":"Point","coordinates":[189900,181900]},"properties":{"FID":34,"PMD_CODE":"AQ/022","PMD_X":189900,"PMD_Y":181900,"PMD_Z":-80,"PN_NAME_E":"Shibli","GR_GOVERNA":"Nablus","LOC_NAME_E":"An Nassariya","PT_POINT_T":"Spring"}},{"type":"Feature","id":35,"geometry":{"type":"Point","coordinates":[187500,182600]},"properties":{"FID":35,"PMD_CODE":"AQ/023","PMD_X":187500,"PMD_Y":182600,"PMD_Z":-50,"PN_NAME_E":"Ya'qub","GR_GOVERNA":"Nablus","LOC_NAME_E":"An Nassariya","PT_POINT_T":"Spring"}},{"type":"Feature","id":36,"geometry":{"type":"Point","coordinates":[186260,183570]},"properties":{"FID":36,"PMD_CODE":"AQ/024","PMD_X":186260,"PMD_Y":183570,"PMD_Z":-19,"PN_NAME_E":"Abu Saleh","GR_GOVERNA":"Nablus","LOC_NAME_E":"Al'Aqrabaniya","PT_POINT_T":"Spring"}},{"type":"Feature","id":37,"geometry":{"type":"Point","coordinates":[187030,182900]},"properties":{"FID":37,"PMD_CODE":"AQ/025","PMD_X":187030,"PMD_Y":182900,"PMD_Z":-38,"PN_NAME_E":"Meskah","GR_GOVERNA":"Nablus","LOC_NAME_E":"Al'Aqrabaniya","PT_POINT_T":"Spring"}},{"type":"Feature","id":38,"geometry":{"type":"Point","coordinates":[182400,188400]},"properties":{"FID":38,"PMD_CODE":"AQ/030","PMD_X":182400,"PMD_Y":188400,"PMD_Z":160,"PN_NAME_E":"Al Far'ah","GR_GOVERNA":"Tubas","LOC_NAME_E":"Ras Al-Far'a","PT_POINT_T":"Spring"}},{"type":"Feature","id":39,"geometry":{"type":"Point","coordinates":[182500,188600]},"properties":{"FID":39,"PMD_CODE":"AQ/031","PMD_X":182500,"PMD_Y":188600,"PMD_Z":160,"PN_NAME_E":"Josala","GR_GOVERNA":"Tubas","LOC_NAME_E":"Ras Al-Far'a","PT_POINT_T":"Spring"}},{"type":"Feature","id":40,"geometry":{"type":"Point","coordinates":[182000,187950]},"properties":{"FID":40,"PMD_CODE":"AQ/032","PMD_X":182000,"PMD_Y":187950,"PMD_Z":155,"PN_NAME_E":"Al Dlaib","GR_GOVERNA":"Tubas","LOC_NAME_E":"Ras Al-Far'a","PT_POINT_T":"Spring"}},{"type":"Feature","id":41,"geometry":{"type":"Point","coordinates":[180700,184800]},"properties":{"FID":41,"PMD_CODE":"AQ/035","PMD_X":180700,"PMD_Y":184800,"PMD_Z":130,"PN_NAME_E":"Abu Zain","GR_GOVERNA":"Nablus","LOC_NAME_E":"Al Badhan","PT_POINT_T":"Spring"}},{"type":"Feature","id":42,"geometry":{"type":"Point","coordinates":[179950,185490]},"properties":{"FID":42,"PMD_CODE":"AQ/036","PMD_X":179950,"PMD_Y":185490,"PMD_Z":240,"PN_NAME_E":"Sedrah","GR_GOVERNA":"Nablus","LOC_NAME_E":"Al Badhan","PT_POINT_T":"Spring"}},{"type":"Feature","id":43,"geometry":{"type":"Point","coordinates":[180120,185320]},"properties":{"FID":43,"PMD_CODE":"AQ/037A","PMD_X":180120,"PMD_Y":185320,"PMD_Z":215,"PN_NAME_E":"Hamad & Baidah","GR_GOVERNA":"Nablus","LOC_NAME_E":"Al Badhan","PT_POINT_T":"Spring"}},{"type":"Feature","id":44,"geometry":{"type":"Point","coordinates":[180130,185280]},"properties":{"FID":44,"PMD_CODE":"AQ/037B","PMD_X":180130,"PMD_Y":185280,"PMD_Z":215,"PN_NAME_E":"Qdairah","GR_GOVERNA":"Nablus","LOC_NAME_E":"Al Badhan","PT_POINT_T":"Spring"}},{"type":"Feature","id":45,"geometry":{"type":"Point","coordinates":[180370,185100]},"properties":{"FID":45,"PMD_CODE":"AQ/038","PMD_X":180370,"PMD_Y":185100,"PMD_Z":170,"PN_NAME_E":"Jeser","GR_GOVERNA":"Nablus","LOC_NAME_E":"Al Badhan","PT_POINT_T":"Spring"}},{"type":"Feature","id":46,"geometry":{"type":"Point","coordinates":[180420,184820]},"properties":{"FID":46,"PMD_CODE":"AQ/039","PMD_X":180420,"PMD_Y":184820,"PMD_Z":160,"PN_NAME_E":"Tabban","GR_GOVERNA":"Nablus","LOC_NAME_E":"Al Badhan","PT_POINT_T":"Spring"}},{"type":"Feature","id":47,"geometry":{"type":"Point","coordinates":[180440,184420]},"properties":{"FID":47,"PMD_CODE":"AQ/040","PMD_X":180440,"PMD_Y":184420,"PMD_Z":130,"PN_NAME_E":"Al Subyan","GR_GOVERNA":"Nablus","LOC_NAME_E":"Al Badhan","PT_POINT_T":"Spring"}},{"type":"Feature","id":48,"geometry":{"type":"Point","coordinates":[180300,184600]},"properties":{"FID":48,"PMD_CODE":"AQ/041","PMD_X":180300,"PMD_Y":184600,"PMD_Z":0,"PN_NAME_E":"Nazzaz Sajur","GR_GOVERNA":"Nablus","LOC_NAME_E":"Al Badhan","PT_POINT_T":"Spring"}},{"type":"Feature","id":49,"geometry":{"type":"Point","coordinates":[177300,180100]},"properties":{"FID":49,"PMD_CODE":"AQ/042","PMD_X":177300,"PMD_Y":180100,"PMD_Z":540,"PN_NAME_E":"'Askar","GR_GOVERNA":"Nablus","LOC_NAME_E":"'Askar Camp","PT_POINT_T":"Spring"}},{"type":"Feature","id":50,"geometry":{"type":"Point","coordinates":[176840,179770]},"properties":{"FID":50,"PMD_CODE":"AQ/043","PMD_X":176840,"PMD_Y":179770,"PMD_Z":510,"PN_NAME_E":"Balata","GR_GOVERNA":"Nablus","LOC_NAME_E":"Balatah","PT_POINT_T":"Spring"}},{"type":"Feature","id":51,"geometry":{"type":"Point","coordinates":[176200,179900]},"properties":{"FID":51,"PMD_CODE":"AQ/044","PMD_X":176200,"PMD_Y":179900,"PMD_Z":560,"PN_NAME_E":"Dafna","GR_GOVERNA":"Nablus","LOC_NAME_E":"Nablus","PT_POINT_T":"Spring"}},{"type":"Feature","id":52,"geometry":{"type":"Point","coordinates":[177000,179500]},"properties":{"FID":52,"PMD_CODE":"AQ/045","PMD_X":177000,"PMD_Y":179500,"PMD_Z":520,"PN_NAME_E":"Abu Hammar","GR_GOVERNA":"Nablus","LOC_NAME_E":"Balatah","PT_POINT_T":"Spring"}},{"type":"Feature","id":53,"geometry":{"type":"Point","coordinates":[176800,179000]},"properties":{"FID":53,"PMD_CODE":"AQ/046","PMD_X":176800,"PMD_Y":179000,"PMD_Z":550,"PN_NAME_E":"Sarin","GR_GOVERNA":"Nablus","LOC_NAME_E":"Balatah","PT_POINT_T":"Spring"}},{"type":"Feature","id":54,"geometry":{"type":"Point","coordinates":[176800,178800]},"properties":{"FID":54,"PMD_CODE":"AQ/047","PMD_X":176800,"PMD_Y":178800,"PMD_Z":580,"PN_NAME_E":"Al Subyan","GR_GOVERNA":"Nablus","LOC_NAME_E":"Balatah","PT_POINT_T":"Spring"}},{"type":"Feature","id":55,"geometry":{"type":"Point","coordinates":[186750,151420]},"properties":{"FID":55,"PMD_CODE":"AR/020","PMD_X":186750,"PMD_Y":151420,"PMD_Z":20,"PN_NAME_E":"Al 'Auja","GR_GOVERNA":"Jericho","LOC_NAME_E":"Al 'Auja","PT_POINT_T":"Spring"}},{"type":"Feature","id":56,"geometry":{"type":"Point","coordinates":[181550,155250]},"properties":{"FID":56,"PMD_CODE":"AR/021","PMD_X":181550,"PMD_Y":155250,"PMD_Z":425,"PN_NAME_E":"Samia","GR_GOVERNA":"Ramallah","LOC_NAME_E":"Kafr Malik","PT_POINT_T":"Spring"}},{"type":"Feature","id":57,"geometry":{"type":"Point","coordinates":[185620,138170]},"properties":{"FID":57,"PMD_CODE":"AS/020","PMD_X":185620,"PMD_Y":138170,"PMD_Z":10,"PN_NAME_E":"Al Qilt & Al Fawwar","GR_GOVERNA":"Jericho","LOC_NAME_E":"Wadi Al Qilt","PT_POINT_T":"Spring"}},{"type":"Feature","id":58,"geometry":{"type":"Point","coordinates":[183180,138600]},"properties":{"FID":58,"PMD_CODE":"AS/021","PMD_X":183180,"PMD_Y":138600,"PMD_Z":75,"PN_NAME_E":"Al Fawwar","GR_GOVERNA":"Jerusalem","LOC_NAME_E":"Wadi Al Qilt","PT_POINT_T":"Spring"}},{"type":"Feature","id":59,"geometry":{"type":"Point","coordinates":[178720,137860]},"properties":{"FID":59,"PMD_CODE":"AS/022","PMD_X":178720,"PMD_Y":137860,"PMD_Z":290,"PN_NAME_E":"Fara","GR_GOVERNA":"Jerusalem","LOC_NAME_E":"Ein Fara","PT_POINT_T":"Spring"}},{"type":"Feature","id":60,"geometry":{"type":"Point","coordinates":[179070,137770]},"properties":{"FID":60,"PMD_CODE":"AS/022A","PMD_X":179070,"PMD_Y":137770,"PMD_Z":285,"PN_NAME_E":"Al Jummaizah","GR_GOVERNA":"Jerusalem","LOC_NAME_E":"Wadi Al Qilt","PT_POINT_T":"Spring"}},{"type":"Feature","id":61,"geometry":{"type":"Point","coordinates":[179280,137760]},"properties":{"FID":61,"PMD_CODE":"AS/022B","PMD_X":179280,"PMD_Y":137760,"PMD_Z":250,"PN_NAME_E":"Al Ru'yan","GR_GOVERNA":"Jerusalem","LOC_NAME_E":"Wadi Al Qilt","PT_POINT_T":"Spring"}},{"type":"Feature","id":62,"geometry":{"type":"Point","coordinates":[169200,146100]},"properties":{"FID":62,"PMD_CODE":"AS/025","PMD_X":169200,"PMD_Y":146100,"PMD_Z":850,"PN_NAME_E":"Al Bira","GR_GOVERNA":"Ramallah","LOC_NAME_E":"Al Bira","PT_POINT_T":"Spring"}},{"type":"Feature","id":63,"geometry":{"type":"Point","coordinates":[172800,147900]},"properties":{"FID":63,"PMD_CODE":"AS/026","PMD_X":172800,"PMD_Y":147900,"PMD_Z":880,"PN_NAME_E":"Beitin","GR_GOVERNA":"Ramallah","LOC_NAME_E":"Beitin","PT_POINT_T":"Spring"}},{"type":"Feature","id":64,"geometry":{"type":"Point","coordinates":[174310,180210]},"properties":{"FID":64,"PMD_CODE":"BA/020","PMD_X":174310,"PMD_Y":180210,"PMD_Z":620,"PN_NAME_E":"Ras Al 'Ein","GR_GOVERNA":"Nablus","LOC_NAME_E":"Nablus","PT_POINT_T":"Spring"}},{"type":"Feature","id":65,"geometry":{"type":"Point","coordinates":[174450,180400]},"properties":{"FID":65,"PMD_CODE":"BA/021","PMD_X":174450,"PMD_Y":180400,"PMD_Z":575,"PN_NAME_E":"Al 'Asal","GR_GOVERNA":"Nablus","LOC_NAME_E":"Nablus","PT_POINT_T":"Spring"}},{"type":"Feature","id":66,"geometry":{"type":"Point","coordinates":[174680,180600]},"properties":{"FID":66,"PMD_CODE":"BA/022","PMD_X":174680,"PMD_Y":180600,"PMD_Z":550,"PN_NAME_E":"Qaryun","GR_GOVERNA":"Nablus","LOC_NAME_E":"Nablus","PT_POINT_T":"Spring"}},{"type":"Feature","id":67,"geometry":{"type":"Point","coordinates":[174700,180920]},"properties":{"FID":67,"PMD_CODE":"BA/023","PMD_X":174700,"PMD_Y":180920,"PMD_Z":510,"PN_NAME_E":"Shraish","GR_GOVERNA":"Nablus","LOC_NAME_E":"Nablus","PT_POINT_T":"Spring"}},{"type":"Feature","id":68,"geometry":{"type":"Point","coordinates":[174600,181100]},"properties":{"FID":68,"PMD_CODE":"BA/024","PMD_X":174600,"PMD_Y":181100,"PMD_Z":510,"PN_NAME_E":"Al Qasab","GR_GOVERNA":"Nablus","LOC_NAME_E":"Nablus","PT_POINT_T":"Spring"}},{"type":"Feature","id":69,"geometry":{"type":"Point","coordinates":[174800,181040]},"properties":{"FID":69,"PMD_CODE":"BA/025","PMD_X":174800,"PMD_Y":181040,"PMD_Z":510,"PN_NAME_E":"Fu'ad","GR_GOVERNA":"Nablus","LOC_NAME_E":"Nablus","PT_POINT_T":"Spring"}},{"type":"Feature","id":70,"geometry":{"type":"Point","coordinates":[174800,181200]},"properties":{"FID":70,"PMD_CODE":"BA/026","PMD_X":174800,"PMD_Y":181200,"PMD_Z":540,"PN_NAME_E":"Al-Kufeir","GR_GOVERNA":"Nablus","LOC_NAME_E":"Nablus","PT_POINT_T":"Spring"}},{"type":"Feature","id":71,"geometry":{"type":"Point","coordinates":[173450,181630]},"properties":{"FID":71,"PMD_CODE":"BA/027","PMD_X":173450,"PMD_Y":181630,"PMD_Z":470,"PN_NAME_E":"Al Subyan","GR_GOVERNA":"Nablus","LOC_NAME_E":"Nablus","PT_POINT_T":"Spring"}},{"type":"Feature","id":72,"geometry":{"type":"Point","coordinates":[173500,181840]},"properties":{"FID":72,"PMD_CODE":"BA/028","PMD_X":173500,"PMD_Y":181840,"PMD_Z":458,"PN_NAME_E":"Beit Al Ma'","GR_GOVERNA":"Nablus","LOC_NAME_E":"Nablus","PT_POINT_T":"Spring"}},{"type":"Feature","id":73,"geometry":{"type":"Point","coordinates":[]},"properties":{"FID":73,"PMD_CODE":"BA/029","PMD_X":0,"PMD_Y":0,"PMD_Z":0,"PN_NAME_E":"Al Bassah","GR_GOVERNA":"Nablus","LOC_NAME_E":"Nablus","PT_POINT_T":"Spring"}},{"type":"Feature","id":74,"geometry":{"type":"Point","coordinates":[172600,180850]},"properties":{"FID":74,"PMD_CODE":"BA/031","PMD_X":172600,"PMD_Y":180850,"PMD_Z":560,"PN_NAME_E":"Al Jame'","GR_GOVERNA":"Nablus","LOC_NAME_E":"Nablus","PT_POINT_T":"Spring"}},{"type":"Feature","id":75,"geometry":{"type":"Point","coordinates":[172500,180900]},"properties":{"FID":75,"PMD_CODE":"BA/032","PMD_X":172500,"PMD_Y":180900,"PMD_Z":550,"PN_NAME_E":"I'waidah","GR_GOVERNA":"Nablus","LOC_NAME_E":"Nablus","PT_POINT_T":"Spring"}},{"type":"Feature","id":76,"geometry":{"type":"Point","coordinates":[171650,183940]},"properties":{"FID":76,"PMD_CODE":"BA/033","PMD_X":171650,"PMD_Y":183940,"PMD_Z":410,"PN_NAME_E":"Zawata","GR_GOVERNA":"Nablus","LOC_NAME_E":"Zawata","PT_POINT_T":"Spring"}},{"type":"Feature","id":77,"geometry":{"type":"Point","coordinates":[169190,184600]},"properties":{"FID":77,"PMD_CODE":"BA/034","PMD_X":169190,"PMD_Y":184600,"PMD_Z":425,"PN_NAME_E":"Kfar Farat","GR_GOVERNA":"Nablus","LOC_NAME_E":"Deir Sharaf","PT_POINT_T":"Spring"}},{"type":"Feature","id":78,"geometry":{"type":"Point","coordinates":[169500,185780]},"properties":{"FID":78,"PMD_CODE":"BA/035","PMD_X":169500,"PMD_Y":185780,"PMD_Z":445,"PN_NAME_E":"Harun","GR_GOVERNA":"Nablus","LOC_NAME_E":"An Naqura","PT_POINT_T":"Spring"}},{"type":"Feature","id":79,"geometry":{"type":"Point","coordinates":[170580,186320]},"properties":{"FID":79,"PMD_CODE":"BA/036","PMD_X":170580,"PMD_Y":186320,"PMD_Z":435,"PN_NAME_E":"Ijnisinya","GR_GOVERNA":"Nablus","LOC_NAME_E":"Ijnisinya","PT_POINT_T":"Spring"}},{"type":"Feature","id":80,"geometry":{"type":"Point","coordinates":[170800,186000]},"properties":{"FID":80,"PMD_CODE":"BA/037","PMD_X":170800,"PMD_Y":186000,"PMD_Z":775,"PN_NAME_E":"Tayyoun","GR_GOVERNA":"Nablus","LOC_NAME_E":"Ijnisinya","PT_POINT_T":"Spring"}},{"type":"Feature","id":81,"geometry":{"type":"Point","coordinates":[171000,186000]},"properties":{"FID":81,"PMD_CODE":"BA/038","PMD_X":171000,"PMD_Y":186000,"PMD_Z":775,"PN_NAME_E":"Az Zawiya","GR_GOVERNA":"Nablus","LOC_NAME_E":"Ijnisinya","PT_POINT_T":"Spring"}},{"type":"Feature","id":82,"geometry":{"type":"Point","coordinates":[171100,187800]},"properties":{"FID":82,"PMD_CODE":"BA/040","PMD_X":171100,"PMD_Y":187800,"PMD_Z":380,"PN_NAME_E":"Al Sharqiyyah","GR_GOVERNA":"Nablus","LOC_NAME_E":"Nisf Jubeil","PT_POINT_T":"Spring"}},{"type":"Feature","id":83,"geometry":{"type":"Point","coordinates":[170850,187750]},"properties":{"FID":83,"PMD_CODE":"BA/041","PMD_X":170850,"PMD_Y":187750,"PMD_Z":390,"PN_NAME_E":"Al Khadr","GR_GOVERNA":"Nablus","LOC_NAME_E":"Nisf Jubeil","PT_POINT_T":"Spring"}},{"type":"Feature","id":84,"geometry":{"type":"Point","coordinates":[171000,187500]},"properties":{"FID":84,"PMD_CODE":"BA/042","PMD_X":171000,"PMD_Y":187500,"PMD_Z":425,"PN_NAME_E":"Ibraheem","GR_GOVERNA":"Nablus","LOC_NAME_E":"Nisf Jubeil","PT_POINT_T":"Spring"}},{"type":"Feature","id":85,"geometry":{"type":"Point","coordinates":[170900,187900]},"properties":{"FID":85,"PMD_CODE":"BA/043","PMD_X":170900,"PMD_Y":187900,"PMD_Z":380,"PN_NAME_E":"Muwaziyyah","GR_GOVERNA":"Nablus","LOC_NAME_E":"Nisf Jubeil","PT_POINT_T":"Spring"}},{"type":"Feature","id":86,"geometry":{"type":"Point","coordinates":[170700,188840]},"properties":{"FID":86,"PMD_CODE":"BA/044","PMD_X":170700,"PMD_Y":188840,"PMD_Z":410,"PN_NAME_E":"Al Balad","GR_GOVERNA":"Nablus","LOC_NAME_E":"Beit Imrin","PT_POINT_T":"Spring"}},{"type":"Feature","id":87,"geometry":{"type":"Point","coordinates":[170100,188900]},"properties":{"FID":87,"PMD_CODE":"BA/045","PMD_X":170100,"PMD_Y":188900,"PMD_Z":425,"PN_NAME_E":"Yan","GR_GOVERNA":"Nablus","LOC_NAME_E":"Beit Imrin","PT_POINT_T":"Spring"}},{"type":"Feature","id":88,"geometry":{"type":"Point","coordinates":[168700,189700]},"properties":{"FID":88,"PMD_CODE":"BA/046","PMD_X":168700,"PMD_Y":189700,"PMD_Z":480,"PN_NAME_E":"Burqa Group","GR_GOVERNA":"Nablus","LOC_NAME_E":"Burqa","PT_POINT_T":"Spring"}},{"type":"Feature","id":89,"geometry":{"type":"Point","coordinates":[168800,189900]},"properties":{"FID":89,"PMD_CODE":"BA/047","PMD_X":168800,"PMD_Y":189900,"PMD_Z":475,"PN_NAME_E":"Al Hud","GR_GOVERNA":"Nablus","LOC_NAME_E":"Burqa","PT_POINT_T":"Spring"}},{"type":"Feature","id":90,"geometry":{"type":"Point","coordinates":[168400,189700]},"properties":{"FID":90,"PMD_CODE":"BA/048","PMD_X":168400,"PMD_Y":189700,"PMD_Z":450,"PN_NAME_E":"Al Fawwar","GR_GOVERNA":"Nablus","LOC_NAME_E":"Burqa","PT_POINT_T":"Spring"}},{"type":"Feature","id":91,"geometry":{"type":"Point","coordinates":[167800,191100]},"properties":{"FID":91,"PMD_CODE":"BA/050","PMD_X":167800,"PMD_Y":191100,"PMD_Z":500,"PN_NAME_E":"Zakariyya","GR_GOVERNA":"Jenin","LOC_NAME_E":"Silat adh Dhahr","PT_POINT_T":"Spring"}},{"type":"Feature","id":92,"geometry":{"type":"Point","coordinates":[168250,191250]},"properties":{"FID":92,"PMD_CODE":"BA/051","PMD_X":168250,"PMD_Y":191250,"PMD_Z":475,"PN_NAME_E":"Hud","GR_GOVERNA":"Jenin","LOC_NAME_E":"Silat adh Dhahr","PT_POINT_T":"Spring"}},{"type":"Feature","id":93,"geometry":{"type":"Point","coordinates":[168000,191200]},"properties":{"FID":93,"PMD_CODE":"BA/052","PMD_X":168000,"PMD_Y":191200,"PMD_Z":500,"PN_NAME_E":"Zaban","GR_GOVERNA":"Jenin","LOC_NAME_E":"Silat adh Dhahr","PT_POINT_T":"Spring"}},{"type":"Feature","id":94,"geometry":{"type":"Point","coordinates":[168000,191200]},"properties":{"FID":94,"PMD_CODE":"BA/053","PMD_X":168000,"PMD_Y":191200,"PMD_Z":500,"PN_NAME_E":"Lowya","GR_GOVERNA":"Jenin","LOC_NAME_E":"Silat adh Dhahr","PT_POINT_T":"Spring"}},{"type":"Feature","id":95,"geometry":{"type":"Point","coordinates":[169200,191900]},"properties":{"FID":95,"PMD_CODE":"BA/054","PMD_X":169200,"PMD_Y":191900,"PMD_Z":430,"PN_NAME_E":"Al Kufur","GR_GOVERNA":"Jenin","LOC_NAME_E":"Al-Fandaqumiya","PT_POINT_T":"Spring"}},{"type":"Feature","id":96,"geometry":{"type":"Point","coordinates":[169200,192050]},"properties":{"FID":96,"PMD_CODE":"BA/055","PMD_X":169200,"PMD_Y":192050,"PMD_Z":410,"PN_NAME_E":"Al Hawuz","GR_GOVERNA":"Jenin","LOC_NAME_E":"Al-Fandaqumiya","PT_POINT_T":"Spring"}},{"type":"Feature","id":97,"geometry":{"type":"Point","coordinates":[169450,191850]},"properties":{"FID":97,"PMD_CODE":"BA/056","PMD_X":169450,"PMD_Y":191850,"PMD_Z":460,"PN_NAME_E":"Al Balad","GR_GOVERNA":"Jenin","LOC_NAME_E":"Al-Fandaqumiya","PT_POINT_T":"Spring"}},{"type":"Feature","id":98,"geometry":{"type":"Point","coordinates":[171600,192250]},"properties":{"FID":98,"PMD_CODE":"BA/057","PMD_X":171600,"PMD_Y":192250,"PMD_Z":370,"PN_NAME_E":"Al Sharqiyyah","GR_GOVERNA":"Jenin","LOC_NAME_E":"Jaba'","PT_POINT_T":"Spring"}},{"type":"Feature","id":99,"geometry":{"type":"Point","coordinates":[170940,192280]},"properties":{"FID":99,"PMD_CODE":"BA/058","PMD_X":170940,"PMD_Y":192280,"PMD_Z":390,"PN_NAME_E":"Al Juzah","GR_GOVERNA":"Jenin","LOC_NAME_E":"Jaba'","PT_POINT_T":"Spring"}},{"type":"Feature","id":100,"geometry":{"type":"Point","coordinates":[178620,207600]},"properties":{"FID":100,"PMD_CODE":"BA/060","PMD_X":178620,"PMD_Y":207600,"PMD_Z":215,"PN_NAME_E":"Jenin Al Balad","GR_GOVERNA":"Jenin","LOC_NAME_E":"Jenin","PT_POINT_T":"Spring"}},{"type":"Feature","id":101,"geometry":{"type":"Point","coordinates":[178200,206500]},"properties":{"FID":101,"PMD_CODE":"BA/061","PMD_X":178200,"PMD_Y":206500,"PMD_Z":175,"PN_NAME_E":"Al Sharifeh","GR_GOVERNA":"Jenin","LOC_NAME_E":"Jenin","PT_POINT_T":"Spring"}},{"type":"Feature","id":102,"geometry":{"type":"Point","coordinates":[178100,206000]},"properties":{"FID":102,"PMD_CODE":"BA/061A","PMD_X":178100,"PMD_Y":206000,"PMD_Z":175,"PN_NAME_E":"Nienia","GR_GOVERNA":"Jenin","LOC_NAME_E":"Jenin","PT_POINT_T":"Spring"}},{"type":"Feature","id":103,"geometry":{"type":"Point","coordinates":[175120,207350]},"properties":{"FID":103,"PMD_CODE":"BA/062","PMD_X":175120,"PMD_Y":207350,"PMD_Z":195,"PN_NAME_E":"Birqin Al Balad","GR_GOVERNA":"Jenin","LOC_NAME_E":"Birqin","PT_POINT_T":"Spring"}},{"type":"Feature","id":104,"geometry":{"type":"Point","coordinates":[165700,212200]},"properties":{"FID":104,"PMD_CODE":"BA/063","PMD_X":165700,"PMD_Y":212200,"PMD_Z":410,"PN_NAME_E":"Al Nab'a","GR_GOVERNA":"Jenin","LOC_NAME_E":"'Anin","PT_POINT_T":"Spring"}},{"type":"Feature","id":105,"geometry":{"type":"Point","coordinates":[165400,211800]},"properties":{"FID":105,"PMD_CODE":"BA/064","PMD_X":165400,"PMD_Y":211800,"PMD_Z":425,"PN_NAME_E":"Ifdai'","GR_GOVERNA":"Jenin","LOC_NAME_E":"'Anin","PT_POINT_T":"Spring"}},{"type":"Feature","id":106,"geometry":{"type":"Point","coordinates":[165600,212100]},"properties":{"FID":106,"PMD_CODE":"BA/065","PMD_X":165600,"PMD_Y":212100,"PMD_Z":430,"PN_NAME_E":"Zaytunah","GR_GOVERNA":"Jenin","LOC_NAME_E":"'Anin","PT_POINT_T":"Spring"}},{"type":"Feature","id":107,"geometry":{"type":"Point","coordinates":[159880,209350]},"properties":{"FID":107,"PMD_CODE":"BA/066","PMD_X":159880,"PMD_Y":209350,"PMD_Z":215,"PN_NAME_E":"Barta'a","GR_GOVERNA":"Jenin","LOC_NAME_E":"Barta'a ash Sharqiya","PT_POINT_T":"Spring"}},{"type":"Feature","id":108,"geometry":{"type":"Point","coordinates":[]},"properties":{"FID":108,"PMD_CODE":"BA/066A","PMD_X":0,"PMD_Y":0,"PMD_Z":0,"PN_NAME_E":"Barta'a Al Gharbiyyah","GR_GOVERNA":"Jenin","LOC_NAME_E":"Barta'a ash Sharqiya","PT_POINT_T":"Spring"}},{"type":"Feature","id":109,"geometry":{"type":"Point","coordinates":[172200,178650]},"properties":{"FID":109,"PMD_CODE":"BA/070","PMD_X":172200,"PMD_Y":178650,"PMD_Z":630,"PN_NAME_E":"Al Balad","GR_GOVERNA":"Nablus","LOC_NAME_E":"Iraq burin","PT_POINT_T":"Spring"}},{"type":"Feature","id":110,"geometry":{"type":"Point","coordinates":[174000,179000]},"properties":{"FID":110,"PMD_CODE":"BA/071","PMD_X":174000,"PMD_Y":179000,"PMD_Z":590,"PN_NAME_E":"Al Fawwar","GR_GOVERNA":"Nablus","LOC_NAME_E":"Iraq burin","PT_POINT_T":"Spring"}},{"type":"Feature","id":111,"geometry":{"type":"Point","coordinates":[]},"properties":{"FID":111,"PMD_CODE":"BA/071A","PMD_X":0,"PMD_Y":0,"PMD_Z":0,"PN_NAME_E":"Mezrab","GR_GOVERNA":"Nablus","LOC_NAME_E":"Iraq burin","PT_POINT_T":"Spring"}},{"type":"Feature","id":112,"geometry":{"type":"Point","coordinates":[178000,174300]},"properties":{"FID":112,"PMD_CODE":"BA/072","PMD_X":178000,"PMD_Y":174300,"PMD_Z":590,"PN_NAME_E":"'Awarta","GR_GOVERNA":"Nablus","LOC_NAME_E":"'Awarta","PT_POINT_T":"Spring"}},{"type":"Feature","id":113,"geometry":{"type":"Point","coordinates":[173800,176650]},"properties":{"FID":113,"PMD_CODE":"BA/073","PMD_X":173800,"PMD_Y":176650,"PMD_Z":575,"PN_NAME_E":"Al Balad","GR_GOVERNA":"Nablus","LOC_NAME_E":"Burin","PT_POINT_T":"Spring"}},{"type":"Feature","id":114,"geometry":{"type":"Point","coordinates":[174080,176620]},"properties":{"FID":114,"PMD_CODE":"BA/074","PMD_X":174080,"PMD_Y":176620,"PMD_Z":580,"PN_NAME_E":"Al Sharqiyyah","GR_GOVERNA":"Nablus","LOC_NAME_E":"Burin","PT_POINT_T":"Spring"}},{"type":"Feature","id":115,"geometry":{"type":"Point","coordinates":[172330,176680]},"properties":{"FID":115,"PMD_CODE":"BA/075","PMD_X":172330,"PMD_Y":176680,"PMD_Z":615,"PN_NAME_E":"Al Sha'ra","GR_GOVERNA":"Nablus","LOC_NAME_E":"Madama","PT_POINT_T":"Spring"}},{"type":"Feature","id":116,"geometry":{"type":"Point","coordinates":[174280,173200]},"properties":{"FID":116,"PMD_CODE":"BA/076","PMD_X":174280,"PMD_Y":173200,"PMD_Z":550,"PN_NAME_E":"Al Balad","GR_GOVERNA":"Nablus","LOC_NAME_E":"Huwwara","PT_POINT_T":"Spring"}},{"type":"Feature","id":117,"geometry":{"type":"Point","coordinates":[163500,171000]},"properties":{"FID":117,"PMD_CODE":"BA/077","PMD_X":163500,"PMD_Y":171000,"PMD_Z":400,"PN_NAME_E":"Kaffet 'Udah","GR_GOVERNA":"Salfit","LOC_NAME_E":"Deir Istiya","PT_POINT_T":"Spring"}},{"type":"Feature","id":118,"geometry":{"type":"Point","coordinates":[160800,173900]},"properties":{"FID":118,"PMD_CODE":"BA/078","PMD_X":160800,"PMD_Y":173900,"PMD_Z":240,"PN_NAME_E":"Al Fawwar","GR_GOVERNA":"Salfit","LOC_NAME_E":"Deir Istiya","PT_POINT_T":"Spring"}},{"type":"Feature","id":119,"geometry":{"type":"Point","coordinates":[161100,173800]},"properties":{"FID":119,"PMD_CODE":"BA/079","PMD_X":161100,"PMD_Y":173800,"PMD_Z":250,"PN_NAME_E":"Al Juzah","GR_GOVERNA":"Salfit","LOC_NAME_E":"Deir Istiya","PT_POINT_T":"Spring"}},{"type":"Feature","id":120,"geometry":{"type":"Point","coordinates":[160400,173700]},"properties":{"FID":120,"PMD_CODE":"BA/080","PMD_X":160400,"PMD_Y":173700,"PMD_Z":250,"PN_NAME_E":"Al Bassah","GR_GOVERNA":"Salfit","LOC_NAME_E":"Deir Istiya","PT_POINT_T":"Spring"}},{"type":"Feature","id":121,"geometry":{"type":"Point","coordinates":[161500,173400]},"properties":{"FID":121,"PMD_CODE":"BA/081","PMD_X":161500,"PMD_Y":173400,"PMD_Z":290,"PN_NAME_E":"Al Moqodeh","GR_GOVERNA":"Nablus","LOC_NAME_E":"Deir Istiya","PT_POINT_T":"Spring"}},{"type":"Feature","id":122,"geometry":{"type":"Point","coordinates":[]},"properties":{"FID":122,"PMD_CODE":"BA/084","PMD_X":0,"PMD_Y":0,"PMD_Z":0,"PN_NAME_E":"Al Balad","GR_GOVERNA":"Salfit","LOC_NAME_E":"Yasuf","PT_POINT_T":"Spring"}},{"type":"Feature","id":123,"geometry":{"type":"Point","coordinates":[]},"properties":{"FID":123,"PMD_CODE":"BA/084A","PMD_X":0,"PMD_Y":0,"PMD_Z":0,"PN_NAME_E":"Delbah","GR_GOVERNA":"Salfit","LOC_NAME_E":"Yasuf","PT_POINT_T":"Spring"}},{"type":"Feature","id":124,"geometry":{"type":"Point","coordinates":[162400,165500]},"properties":{"FID":124,"PMD_CODE":"BA/085","PMD_X":162400,"PMD_Y":165500,"PMD_Z":375,"PN_NAME_E":"Al Matwi","GR_GOVERNA":"Salfit","LOC_NAME_E":"Salfit","PT_POINT_T":"Spring"}},{"type":"Feature","id":125,"geometry":{"type":"Point","coordinates":[166860,165920]},"properties":{"FID":125,"PMD_CODE":"BA/085A","PMD_X":166860,"PMD_Y":165920,"PMD_Z":470,"PN_NAME_E":"Shamiyyah","GR_GOVERNA":"Salfit","LOC_NAME_E":"Salfit","PT_POINT_T":"Spring"}},{"type":"Feature","id":126,"geometry":{"type":"Point","coordinates":[]},"properties":{"FID":126,"PMD_CODE":"BA/085B","PMD_X":0,"PMD_Y":0,"PMD_Z":0,"PN_NAME_E":"Al Matwi Seeps","GR_GOVERNA":"Salfit","LOC_NAME_E":"Salfit","PT_POINT_T":"Spring"}},{"type":"Feature","id":127,"geometry":{"type":"Point","coordinates":[163400,164600]},"properties":{"FID":127,"PMD_CODE":"BA/086","PMD_X":163400,"PMD_Y":164600,"PMD_Z":390,"PN_NAME_E":"Al Shallal","GR_GOVERNA":"Salfit","LOC_NAME_E":"Salfit","PT_POINT_T":"Spring"}},{"type":"Feature","id":128,"geometry":{"type":"Point","coordinates":[164300,165600]},"properties":{"FID":128,"PMD_CODE":"BA/087","PMD_X":164300,"PMD_Y":165600,"PMD_Z":390,"PN_NAME_E":"'Adas","GR_GOVERNA":"Salfit","LOC_NAME_E":"Salfit","PT_POINT_T":"Spring"}},{"type":"Feature","id":129,"geometry":{"type":"Point","coordinates":[173700,162900]},"properties":{"FID":129,"PMD_CODE":"BA/088","PMD_X":173700,"PMD_Y":162900,"PMD_Z":500,"PN_NAME_E":"Al Sha'er","GR_GOVERNA":"Ramallah","LOC_NAME_E":"Al Lubban ash Sharqiya","PT_POINT_T":"Spring"}},{"type":"Feature","id":130,"geometry":{"type":"Point","coordinates":[170700,165200]},"properties":{"FID":130,"PMD_CODE":"BA/089","PMD_X":170700,"PMD_Y":165200,"PMD_Z":570,"PN_NAME_E":"Al Lubban","GR_GOVERNA":"Nablus","LOC_NAME_E":"Al Lubban ash Sharqiya","PT_POINT_T":"Spring"}},{"type":"Feature","id":131,"geometry":{"type":"Point","coordinates":[180030,155800]},"properties":{"FID":131,"PMD_CODE":"BA/090","PMD_X":180030,"PMD_Y":155800,"PMD_Z":740,"PN_NAME_E":"Jurish","GR_GOVERNA":"Ramallah","LOC_NAME_E":"Jurish","PT_POINT_T":"Spring"}},{"type":"Feature","id":132,"geometry":{"type":"Point","coordinates":[178300,165800]},"properties":{"FID":132,"PMD_CODE":"BA/091","PMD_X":178300,"PMD_Y":165800,"PMD_Z":630,"PN_NAME_E":"Momiya","GR_GOVERNA":"Nablus","LOC_NAME_E":"Talfit","PT_POINT_T":"Spring"}},{"type":"Feature","id":133,"geometry":{"type":"Point","coordinates":[178300,165900]},"properties":{"FID":133,"PMD_CODE":"BA/092","PMD_X":178300,"PMD_Y":165900,"PMD_Z":800,"PN_NAME_E":"Al'Eina","GR_GOVERNA":"Nablus","LOC_NAME_E":"Talfit","PT_POINT_T":"Spring"}},{"type":"Feature","id":134,"geometry":{"type":"Point","coordinates":[178380,165700]},"properties":{"FID":134,"PMD_CODE":"BA/093","PMD_X":178380,"PMD_Y":165700,"PMD_Z":640,"PN_NAME_E":"Al Balad","GR_GOVERNA":"Nablus","LOC_NAME_E":"Talfit","PT_POINT_T":"Spring"}},{"type":"Feature","id":135,"geometry":{"type":"Point","coordinates":[177500,163800]},"properties":{"FID":135,"PMD_CODE":"BA/094","PMD_X":177500,"PMD_Y":163800,"PMD_Z":750,"PN_NAME_E":"Qaryut","GR_GOVERNA":"Nablus","LOC_NAME_E":"Qaryut","PT_POINT_T":"Spring"}},{"type":"Feature","id":136,"geometry":{"type":"Point","coordinates":[176800,155600]},"properties":{"FID":136,"PMD_CODE":"BA/095","PMD_X":176800,"PMD_Y":155600,"PMD_Z":690,"PN_NAME_E":"Seilun","GR_GOVERNA":"Ramallah","LOC_NAME_E":"Qaryut","PT_POINT_T":"Spring"}},{"type":"Feature","id":137,"geometry":{"type":"Point","coordinates":[179850,165850]},"properties":{"FID":137,"PMD_CODE":"BA/096","PMD_X":179850,"PMD_Y":165850,"PMD_Z":790,"PN_NAME_E":"Al Balad","GR_GOVERNA":"Nablus","LOC_NAME_E":"Jalud","PT_POINT_T":"Spring"}},{"type":"Feature","id":138,"geometry":{"type":"Point","coordinates":[177200,160300]},"properties":{"FID":138,"PMD_CODE":"BA/100","PMD_X":177200,"PMD_Y":160300,"PMD_Z":680,"PN_NAME_E":"Turmus'ayya","GR_GOVERNA":"Ramallah","LOC_NAME_E":"Turmus'ayya","PT_POINT_T":"Spring"}},{"type":"Feature","id":139,"geometry":{"type":"Point","coordinates":[177400,159000]},"properties":{"FID":139,"PMD_CODE":"BA/100A","PMD_X":177400,"PMD_Y":159000,"PMD_Z":700,"PN_NAME_E":"Al Balad","GR_GOVERNA":"Ramallah","LOC_NAME_E":"Turmus'ayya","PT_POINT_T":"Spring"}},{"type":"Feature","id":140,"geometry":{"type":"Point","coordinates":[175400,160200]},"properties":{"FID":140,"PMD_CODE":"BA/101","PMD_X":175400,"PMD_Y":160200,"PMD_Z":770,"PN_NAME_E":"Sinjil","GR_GOVERNA":"Ramallah","LOC_NAME_E":"Sinjil","PT_POINT_T":"Spring"}},{"type":"Feature","id":141,"geometry":{"type":"Point","coordinates":[174400,160100]},"properties":{"FID":141,"PMD_CODE":"BA/102","PMD_X":174400,"PMD_Y":160100,"PMD_Z":790,"PN_NAME_E":"Um Ghurbah","GR_GOVERNA":"Ramallah","LOC_NAME_E":"Sinjil","PT_POINT_T":"Spring"}},{"type":"Feature","id":142,"geometry":{"type":"Point","coordinates":[171500,160400]},"properties":{"FID":142,"PMD_CODE":"BA/104","PMD_X":171500,"PMD_Y":160400,"PMD_Z":650,"PN_NAME_E":"Sala'","GR_GOVERNA":"Ramallah","LOC_NAME_E":"Jilijliya","PT_POINT_T":"Spring"}},{"type":"Feature","id":143,"geometry":{"type":"Point","coordinates":[171500,160400]},"properties":{"FID":143,"PMD_CODE":"BA/105","PMD_X":171500,"PMD_Y":160400,"PMD_Z":650,"PN_NAME_E":"Al Deek","GR_GOVERNA":"Ramallah","LOC_NAME_E":"Jilijliya","PT_POINT_T":"Spring"}},{"type":"Feature","id":144,"geometry":{"type":"Point","coordinates":[170500,155400]},"properties":{"FID":144,"PMD_CODE":"BA/106","PMD_X":170500,"PMD_Y":155400,"PMD_Z":0,"PN_NAME_E":"Jilijliya Al Balad","GR_GOVERNA":"Ramallah","LOC_NAME_E":"Jilijliya","PT_POINT_T":"Spring"}},{"type":"Feature","id":145,"geometry":{"type":"Point","coordinates":[171900,160200]},"properties":{"FID":145,"PMD_CODE":"BA/107","PMD_X":171900,"PMD_Y":160200,"PMD_Z":680,"PN_NAME_E":"Mendam","GR_GOVERNA":"Ramallah","LOC_NAME_E":"Jilijliya","PT_POINT_T":"Spring"}},{"type":"Feature","id":146,"geometry":{"type":"Point","coordinates":[169100,160300]},"properties":{"FID":146,"PMD_CODE":"BA/108","PMD_X":169100,"PMD_Y":160300,"PMD_Z":570,"PN_NAME_E":"Al Balad","GR_GOVERNA":"Ramallah","LOC_NAME_E":"'Abwein (Bani Zeid ash Sharqiya)","PT_POINT_T":"Spring"}},{"type":"Feature","id":147,"geometry":{"type":"Point","coordinates":[169050,160270]},"properties":{"FID":147,"PMD_CODE":"BA/109","PMD_X":169050,"PMD_Y":160270,"PMD_Z":550,"PN_NAME_E":"Al Sufla","GR_GOVERNA":"Ramallah","LOC_NAME_E":"'Abwein (Bani Zeid ash Sharqiya)","PT_POINT_T":"Spring"}},{"type":"Feature","id":148,"geometry":{"type":"Point","coordinates":[166800,161300]},"properties":{"FID":148,"PMD_CODE":"BA/110","PMD_X":166800,"PMD_Y":161300,"PMD_Z":525,"PN_NAME_E":"Al Balad","GR_GOVERNA":"Ramallah","LOC_NAME_E":"'Arura(Bani Zeid al Sharqiya)","PT_POINT_T":"Spring"}},{"type":"Feature","id":149,"geometry":{"type":"Point","coordinates":[166900,158900]},"properties":{"FID":149,"PMD_CODE":"BA/111","PMD_X":166900,"PMD_Y":158900,"PMD_Z":430,"PN_NAME_E":"'Ajjul","GR_GOVERNA":"Ramallah","LOC_NAME_E":"'Ajjul","PT_POINT_T":"Spring"}},{"type":"Feature","id":150,"geometry":{"type":"Point","coordinates":[]},"properties":{"FID":150,"PMD_CODE":"BA/111A","PMD_X":0,"PMD_Y":0,"PMD_Z":0,"PN_NAME_E":"Darah","GR_GOVERNA":"Ramallah","LOC_NAME_E":"'Ajjul","PT_POINT_T":"Spring"}},{"type":"Feature","id":151,"geometry":{"type":"Point","coordinates":[157300,152400]},"properties":{"FID":151,"PMD_CODE":"BA/112","PMD_X":157300,"PMD_Y":152400,"PMD_Z":460,"PN_NAME_E":"Daqlah","GR_GOVERNA":"Ramallah","LOC_NAME_E":"Umm Safa","PT_POINT_T":"Spring"}},{"type":"Feature","id":152,"geometry":{"type":"Point","coordinates":[160500,159300]},"properties":{"FID":152,"PMD_CODE":"BA/113","PMD_X":160500,"PMD_Y":159300,"PMD_Z":0,"PN_NAME_E":"Abu Fayyad","GR_GOVERNA":"Ramallah","LOC_NAME_E":"Bani Zaid","PT_POINT_T":"Spring"}},{"type":"Feature","id":153,"geometry":{"type":"Point","coordinates":[159000,162400]},"properties":{"FID":153,"PMD_CODE":"BA/114","PMD_X":159000,"PMD_Y":162400,"PMD_Z":330,"PN_NAME_E":"Al Deir","GR_GOVERNA":"Ramallah","LOC_NAME_E":"Bani Zaid","PT_POINT_T":"Spring"}},{"type":"Feature","id":154,"geometry":{"type":"Point","coordinates":[161300,162800]},"properties":{"FID":154,"PMD_CODE":"BA/115","PMD_X":161300,"PMD_Y":162800,"PMD_Z":300,"PN_NAME_E":"Kafer Ein","GR_GOVERNA":"Ramallah","LOC_NAME_E":"Kafr'Ein (Bani Zeid al Gharbiya)","PT_POINT_T":"Spring"}},{"type":"Feature","id":155,"geometry":{"type":"Point","coordinates":[162000,162800]},"properties":{"FID":155,"PMD_CODE":"BA/116","PMD_X":162000,"PMD_Y":162800,"PMD_Z":280,"PN_NAME_E":"Qarawah","GR_GOVERNA":"Ramallah","LOC_NAME_E":"Qarawat Bani Zeid(Bani Zaid al gharbiya)","PT_POINT_T":"Spring"}},{"type":"Feature","id":156,"geometry":{"type":"Point","coordinates":[161350,157250]},"properties":{"FID":156,"PMD_CODE":"BA/117","PMD_X":161350,"PMD_Y":157250,"PMD_Z":485,"PN_NAME_E":"Riya","GR_GOVERNA":"Ramallah","LOC_NAME_E":"Deir Nidham","PT_POINT_T":"Spring"}},{"type":"Feature","id":157,"geometry":{"type":"Point","coordinates":[]},"properties":{"FID":157,"PMD_CODE":"BA/117A","PMD_X":0,"PMD_Y":0,"PMD_Z":0,"PN_NAME_E":"Rayya  Al Fuqa","GR_GOVERNA":"Ramallah","LOC_NAME_E":"Deir Nidham","PT_POINT_T":"Spring"}},{"type":"Feature","id":158,"geometry":{"type":"Point","coordinates":[163700,158400]},"properties":{"FID":158,"PMD_CODE":"BA/118","PMD_X":163700,"PMD_Y":158400,"PMD_Z":340,"PN_NAME_E":"Qasab","GR_GOVERNA":"Ramallah","LOC_NAME_E":"Deir as Sudan","PT_POINT_T":"Spring"}},{"type":"Feature","id":159,"geometry":{"type":"Point","coordinates":[156950,159180]},"properties":{"FID":159,"PMD_CODE":"BA/120","PMD_X":156950,"PMD_Y":159180,"PMD_Z":290,"PN_NAME_E":"Delbah & Laqtan","GR_GOVERNA":"Ramallah","LOC_NAME_E":"'Abud","PT_POINT_T":"Spring"}},{"type":"Feature","id":160,"geometry":{"type":"Point","coordinates":[156880,160080]},"properties":{"FID":160,"PMD_CODE":"BA/121","PMD_X":156880,"PMD_Y":160080,"PMD_Z":255,"PN_NAME_E":"Zarqa","GR_GOVERNA":"Ramallah","LOC_NAME_E":"Bani Zaid","PT_POINT_T":"Spring"}},{"type":"Feature","id":161,"geometry":{"type":"Point","coordinates":[156960,158960]},"properties":{"FID":161,"PMD_CODE":"BA/122","PMD_X":156960,"PMD_Y":158960,"PMD_Z":300,"PN_NAME_E":"Al Mgharah","GR_GOVERNA":"Ramallah","LOC_NAME_E":"'Abud","PT_POINT_T":"Spring"}},{"type":"Feature","id":162,"geometry":{"type":"Point","coordinates":[156870,159310]},"properties":{"FID":162,"PMD_CODE":"BA/123","PMD_X":156870,"PMD_Y":159310,"PMD_Z":0,"PN_NAME_E":"Al 'Alam","GR_GOVERNA":"Ramallah","LOC_NAME_E":"'Abud","PT_POINT_T":"Spring"}},{"type":"Feature","id":163,"geometry":{"type":"Point","coordinates":[158400,163400]},"properties":{"FID":163,"PMD_CODE":"BA/124","PMD_X":158400,"PMD_Y":163400,"PMD_Z":300,"PN_NAME_E":"Al Fawwara","GR_GOVERNA":"Salfit","LOC_NAME_E":"Kafr ad Dik","PT_POINT_T":"Spring"}},{"type":"Feature","id":164,"geometry":{"type":"Point","coordinates":[171600,151200]},"properties":{"FID":164,"PMD_CODE":"BA/126","PMD_X":171600,"PMD_Y":151200,"PMD_Z":750,"PN_NAME_E":"Al Kabeerah","GR_GOVERNA":"Ramallah","LOC_NAME_E":"Dura al Qar'","PT_POINT_T":"Spring"}},{"type":"Feature","id":165,"geometry":{"type":"Point","coordinates":[171600,151050]},"properties":{"FID":165,"PMD_CODE":"BA/127","PMD_X":171600,"PMD_Y":151050,"PMD_Z":760,"PN_NAME_E":"Al Derrah","GR_GOVERNA":"Ramallah","LOC_NAME_E":"Dura al Qar'","PT_POINT_T":"Spring"}},{"type":"Feature","id":166,"geometry":{"type":"Point","coordinates":[171550,151050]},"properties":{"FID":166,"PMD_CODE":"BA/128","PMD_X":171550,"PMD_Y":151050,"PMD_Z":750,"PN_NAME_E":"Al Mgharah","GR_GOVERNA":"Ramallah","LOC_NAME_E":"Dura al Qar'","PT_POINT_T":"Spring"}},{"type":"Feature","id":167,"geometry":{"type":"Point","coordinates":[171600,151150]},"properties":{"FID":167,"PMD_CODE":"BA/129","PMD_X":171600,"PMD_Y":151150,"PMD_Z":740,"PN_NAME_E":"Al Daraj","GR_GOVERNA":"Ramallah","LOC_NAME_E":"Dura al Qar'","PT_POINT_T":"Spring"}},{"type":"Feature","id":168,"geometry":{"type":"Point","coordinates":[171950,153250]},"properties":{"FID":168,"PMD_CODE":"BA/130","PMD_X":171950,"PMD_Y":153250,"PMD_Z":630,"PN_NAME_E":"Al Sharqiyyah","GR_GOVERNA":"Ramallah","LOC_NAME_E":"Ein Siniya","PT_POINT_T":"Spring"}},{"type":"Feature","id":169,"geometry":{"type":"Point","coordinates":[172500,153500]},"properties":{"FID":169,"PMD_CODE":"BA/131","PMD_X":172500,"PMD_Y":153500,"PMD_Z":650,"PN_NAME_E":"Abu Hamdan","GR_GOVERNA":"Ramallah","LOC_NAME_E":"Ein Siniya","PT_POINT_T":"Spring"}},{"type":"Feature","id":170,"geometry":{"type":"Point","coordinates":[171850,153300]},"properties":{"FID":170,"PMD_CODE":"BA/132","PMD_X":171850,"PMD_Y":153300,"PMD_Z":640,"PN_NAME_E":"Shaikh Husain","GR_GOVERNA":"Ramallah","LOC_NAME_E":"Ein Siniya","PT_POINT_T":"Spring"}},{"type":"Feature","id":171,"geometry":{"type":"Point","coordinates":[172300,153800]},"properties":{"FID":171,"PMD_CODE":"BA/133","PMD_X":172300,"PMD_Y":153800,"PMD_Z":675,"PN_NAME_E":"Al Jarab","GR_GOVERNA":"Ramallah","LOC_NAME_E":"Ein Siniya","PT_POINT_T":"Spring"}},{"type":"Feature","id":172,"geometry":{"type":"Point","coordinates":[171800,153800]},"properties":{"FID":172,"PMD_CODE":"BA/134","PMD_X":171800,"PMD_Y":153800,"PMD_Z":675,"PN_NAME_E":"Al Mezrab","GR_GOVERNA":"Ramallah","LOC_NAME_E":"Ein Siniya","PT_POINT_T":"Spring"}},{"type":"Feature","id":173,"geometry":{"type":"Point","coordinates":[171800,153900]},"properties":{"FID":173,"PMD_CODE":"BA/135","PMD_X":171800,"PMD_Y":153900,"PMD_Z":675,"PN_NAME_E":"Al Jurah","GR_GOVERNA":"Ramallah","LOC_NAME_E":"Ein Siniya","PT_POINT_T":"Spring"}},{"type":"Feature","id":174,"geometry":{"type":"Point","coordinates":[170550,152200]},"properties":{"FID":174,"PMD_CODE":"BA/135A","PMD_X":170550,"PMD_Y":152200,"PMD_Z":645,"PN_NAME_E":"Jifna Al Balad","GR_GOVERNA":"Ramallah","LOC_NAME_E":"Jifna","PT_POINT_T":"Spring"}},{"type":"Feature","id":175,"geometry":{"type":"Point","coordinates":[169100,152700]},"properties":{"FID":175,"PMD_CODE":"BA/136","PMD_X":169100,"PMD_Y":152700,"PMD_Z":725,"PN_NAME_E":"Al Marj","GR_GOVERNA":"Ramallah","LOC_NAME_E":"Bir Zeit","PT_POINT_T":"Spring"}},{"type":"Feature","id":176,"geometry":{"type":"Point","coordinates":[161680,157420]},"properties":{"FID":176,"PMD_CODE":"BA/137","PMD_X":161680,"PMD_Y":157420,"PMD_Z":500,"PN_NAME_E":"Al Qus","GR_GOVERNA":"Ramallah","LOC_NAME_E":"Bir Zeit","PT_POINT_T":"Spring"}},{"type":"Feature","id":177,"geometry":{"type":"Point","coordinates":[169100,153270]},"properties":{"FID":177,"PMD_CODE":"BA/138","PMD_X":169100,"PMD_Y":153270,"PMD_Z":730,"PN_NAME_E":"Al Hammam","GR_GOVERNA":"Ramallah","LOC_NAME_E":"Bir Zeit","PT_POINT_T":"Spring"}},{"type":"Feature","id":178,"geometry":{"type":"Point","coordinates":[169100,153500]},"properties":{"FID":178,"PMD_CODE":"BA/139","PMD_X":169100,"PMD_Y":153500,"PMD_Z":745,"PN_NAME_E":"Flaiflah","GR_GOVERNA":"Ramallah","LOC_NAME_E":"Bir Zeit","PT_POINT_T":"Spring"}},{"type":"Feature","id":179,"geometry":{"type":"Point","coordinates":[169900,155000]},"properties":{"FID":179,"PMD_CODE":"BA/140","PMD_X":169900,"PMD_Y":155000,"PMD_Z":100,"PN_NAME_E":"Al Fawwar","GR_GOVERNA":"Ramallah","LOC_NAME_E":"Bir Zeit","PT_POINT_T":"Spring"}},{"type":"Feature","id":180,"geometry":{"type":"Point","coordinates":[170000,155800]},"properties":{"FID":180,"PMD_CODE":"BA/141","PMD_X":170000,"PMD_Y":155800,"PMD_Z":800,"PN_NAME_E":"Abu Shahin","GR_GOVERNA":"Ramallah","LOC_NAME_E":"'Atara","PT_POINT_T":"Spring"}},{"type":"Feature","id":181,"geometry":{"type":"Point","coordinates":[170400,156600]},"properties":{"FID":181,"PMD_CODE":"BA/142","PMD_X":170400,"PMD_Y":156600,"PMD_Z":775,"PN_NAME_E":"Al Balad","GR_GOVERNA":"Ramallah","LOC_NAME_E":"'Atara","PT_POINT_T":"Spring"}},{"type":"Feature","id":182,"geometry":{"type":"Point","coordinates":[169100,156600]},"properties":{"FID":182,"PMD_CODE":"BA/143","PMD_X":169100,"PMD_Y":156600,"PMD_Z":775,"PN_NAME_E":"Hamdiya","GR_GOVERNA":"Ramallah","LOC_NAME_E":"'Atara","PT_POINT_T":"Spring"}},{"type":"Feature","id":183,"geometry":{"type":"Point","coordinates":[168150,150550]},"properties":{"FID":183,"PMD_CODE":"BA/144","PMD_X":168150,"PMD_Y":150550,"PMD_Z":730,"PN_NAME_E":"Majur","GR_GOVERNA":"Ramallah","LOC_NAME_E":"Abu Qash","PT_POINT_T":"Spring"}},{"type":"Feature","id":184,"geometry":{"type":"Point","coordinates":[164700,156000]},"properties":{"FID":184,"PMD_CODE":"BA/150","PMD_X":164700,"PMD_Y":156000,"PMD_Z":625,"PN_NAME_E":"El'abharah","GR_GOVERNA":"Ramallah","LOC_NAME_E":"Jibiya","PT_POINT_T":"Spring"}},{"type":"Feature","id":185,"geometry":{"type":"Point","coordinates":[165700,155000]},"properties":{"FID":185,"PMD_CODE":"BA/151","PMD_X":165700,"PMD_Y":155000,"PMD_Z":600,"PN_NAME_E":"Kobar","GR_GOVERNA":"Ramallah","LOC_NAME_E":"Kobar","PT_POINT_T":"Spring"}},{"type":"Feature","id":186,"geometry":{"type":"Point","coordinates":[166800,152600]},"properties":{"FID":186,"PMD_CODE":"BA/152","PMD_X":166800,"PMD_Y":152600,"PMD_Z":670,"PN_NAME_E":"Al 'Alaq","GR_GOVERNA":"Ramallah","LOC_NAME_E":"Abu Shukheidim","PT_POINT_T":"Spring"}},{"type":"Feature","id":187,"geometry":{"type":"Point","coordinates":[164700,149900]},"properties":{"FID":187,"PMD_CODE":"BA/153","PMD_X":164700,"PMD_Y":149900,"PMD_Z":670,"PN_NAME_E":"Harrashah","GR_GOVERNA":"Ramallah","LOC_NAME_E":"Al Mazra'a al Qibliya","PT_POINT_T":"Spring"}},{"type":"Feature","id":188,"geometry":{"type":"Point","coordinates":[157500,155300]},"properties":{"FID":188,"PMD_CODE":"BA/155","PMD_X":157500,"PMD_Y":155300,"PMD_Z":340,"PN_NAME_E":"Al Zarqah","GR_GOVERNA":"Ramallah","LOC_NAME_E":"Beitillu","PT_POINT_T":"Spring"}},{"type":"Feature","id":189,"geometry":{"type":"Point","coordinates":[152500,155300]},"properties":{"FID":189,"PMD_CODE":"BA/155A","PMD_X":152500,"PMD_Y":155300,"PMD_Z":340,"PN_NAME_E":"Al Zarqah Al Tehta","GR_GOVERNA":"Ramallah","LOC_NAME_E":"Beitillu","PT_POINT_T":"Spring"}},{"type":"Feature","id":190,"geometry":{"type":"Point","coordinates":[159500,155600]},"properties":{"FID":190,"PMD_CODE":"BA/156","PMD_X":159500,"PMD_Y":155600,"PMD_Z":340,"PN_NAME_E":"Al Qwaiqbah","GR_GOVERNA":"Ramallah","LOC_NAME_E":"Beitillu","PT_POINT_T":"Spring"}},{"type":"Feature","id":191,"geometry":{"type":"Point","coordinates":[159700,155600]},"properties":{"FID":191,"PMD_CODE":"BA/157","PMD_X":159700,"PMD_Y":155600,"PMD_Z":350,"PN_NAME_E":"'Akari","GR_GOVERNA":"Ramallah","LOC_NAME_E":"Beitillu","PT_POINT_T":"Spring"}},{"type":"Feature","id":192,"geometry":{"type":"Point","coordinates":[161500,154000]},"properties":{"FID":192,"PMD_CODE":"BA/158","PMD_X":161500,"PMD_Y":154000,"PMD_Z":525,"PN_NAME_E":"Al Balad","GR_GOVERNA":"Ramallah","LOC_NAME_E":"Beitillu","PT_POINT_T":"Spring"}},{"type":"Feature","id":193,"geometry":{"type":"Point","coordinates":[161500,154100]},"properties":{"FID":193,"PMD_CODE":"BA/159","PMD_X":161500,"PMD_Y":154100,"PMD_Z":450,"PN_NAME_E":"Al Qus","GR_GOVERNA":"Ramallah","LOC_NAME_E":"Beitillu","PT_POINT_T":"Spring"}},{"type":"Feature","id":194,"geometry":{"type":"Point","coordinates":[159500,154800]},"properties":{"FID":194,"PMD_CODE":"BA/160","PMD_X":159500,"PMD_Y":154800,"PMD_Z":225,"PN_NAME_E":"Al Sharqiyyah","GR_GOVERNA":"Ramallah","LOC_NAME_E":"Deir 'Ammar","PT_POINT_T":"Spring"}},{"type":"Feature","id":195,"geometry":{"type":"Point","coordinates":[158500,153800]},"properties":{"FID":195,"PMD_CODE":"BA/161","PMD_X":158500,"PMD_Y":153800,"PMD_Z":500,"PN_NAME_E":"Deir 'Ammar","GR_GOVERNA":"Ramallah","LOC_NAME_E":"Deir 'Ammar","PT_POINT_T":"Spring"}},{"type":"Feature","id":196,"geometry":{"type":"Point","coordinates":[159400,153700]},"properties":{"FID":196,"PMD_CODE":"BA/162","PMD_X":159400,"PMD_Y":153700,"PMD_Z":475,"PN_NAME_E":"Al Balad","GR_GOVERNA":"Ramallah","LOC_NAME_E":"Jammala","PT_POINT_T":"Spring"}},{"type":"Feature","id":197,"geometry":{"type":"Point","coordinates":[164380,147920]},"properties":{"FID":197,"PMD_CODE":"BA/163","PMD_X":164380,"PMD_Y":147920,"PMD_Z":510,"PN_NAME_E":"Al Balad","GR_GOVERNA":"Ramallah","LOC_NAME_E":"'Ein Qinya","PT_POINT_T":"Spring"}},{"type":"Feature","id":198,"geometry":{"type":"Point","coordinates":[165370,148700]},"properties":{"FID":198,"PMD_CODE":"BA/164","PMD_X":165370,"PMD_Y":148700,"PMD_Z":500,"PN_NAME_E":"Delbah","GR_GOVERNA":"Ramallah","LOC_NAME_E":"'Ein Qinya","PT_POINT_T":"Spring"}},{"type":"Feature","id":199,"geometry":{"type":"Point","coordinates":[164370,147800]},"properties":{"FID":199,"PMD_CODE":"BA/165","PMD_X":164370,"PMD_Y":147800,"PMD_Z":560,"PN_NAME_E":"Um Al 'Enain","GR_GOVERNA":"Ramallah","LOC_NAME_E":"'Ein Qinya","PT_POINT_T":"Spring"}},{"type":"Feature","id":200,"geometry":{"type":"Point","coordinates":[164500,149200]},"properties":{"FID":200,"PMD_CODE":"BA/166","PMD_X":164500,"PMD_Y":149200,"PMD_Z":490,"PN_NAME_E":"Umm 'Issa","GR_GOVERNA":"Ramallah","LOC_NAME_E":"'Ein Qinya","PT_POINT_T":"Spring"}},{"type":"Feature","id":201,"geometry":{"type":"Point","coordinates":[164400,147800]},"properties":{"FID":201,"PMD_CODE":"BA/167","PMD_X":164400,"PMD_Y":147800,"PMD_Z":525,"PN_NAME_E":"Um Al Rumman","GR_GOVERNA":"Ramallah","LOC_NAME_E":"'Ein Qinya","PT_POINT_T":"Spring"}},{"type":"Feature","id":202,"geometry":{"type":"Point","coordinates":[165300,148900]},"properties":{"FID":202,"PMD_CODE":"BA/168","PMD_X":165300,"PMD_Y":148900,"PMD_Z":550,"PN_NAME_E":"Ras Al Wad","GR_GOVERNA":"Ramallah","LOC_NAME_E":"'Ein Qinya","PT_POINT_T":"Spring"}},{"type":"Feature","id":203,"geometry":{"type":"Point","coordinates":[166300,148900]},"properties":{"FID":203,"PMD_CODE":"BA/169","PMD_X":166300,"PMD_Y":148900,"PMD_Z":570,"PN_NAME_E":"Kufriya","GR_GOVERNA":"Ramallah","LOC_NAME_E":"'Ein Qinya","PT_POINT_T":"Spring"}},{"type":"Feature","id":204,"geometry":{"type":"Point","coordinates":[163630,145880]},"properties":{"FID":204,"PMD_CODE":"BA/170","PMD_X":163630,"PMD_Y":145880,"PMD_Z":535,"PN_NAME_E":"'Arik Al Fuqa","GR_GOVERNA":"Ramallah","LOC_NAME_E":"'Ein 'Arik","PT_POINT_T":"Spring"}},{"type":"Feature","id":205,"geometry":{"type":"Point","coordinates":[163330,146120]},"properties":{"FID":205,"PMD_CODE":"BA/171","PMD_X":163330,"PMD_Y":146120,"PMD_Z":515,"PN_NAME_E":"'Arik Al Tehta","GR_GOVERNA":"Ramallah","LOC_NAME_E":"'Ein 'Arik","PT_POINT_T":"Spring"}},{"type":"Feature","id":206,"geometry":{"type":"Point","coordinates":[163300,145100]},"properties":{"FID":206,"PMD_CODE":"BA/172","PMD_X":163300,"PMD_Y":145100,"PMD_Z":600,"PN_NAME_E":"Al Jaryut","GR_GOVERNA":"Ramallah","LOC_NAME_E":"Beituniya","PT_POINT_T":"Spring"}},{"type":"Feature","id":207,"geometry":{"type":"Point","coordinates":[167200,139400]},"properties":{"FID":207,"PMD_CODE":"BA/175","PMD_X":167200,"PMD_Y":139400,"PMD_Z":115,"PN_NAME_E":"Al Balad","GR_GOVERNA":"Jerusalem","LOC_NAME_E":"Al Jib","PT_POINT_T":"Spring"}},{"type":"Feature","id":208,"geometry":{"type":"Point","coordinates":[166700,140400]},"properties":{"FID":208,"PMD_CODE":"BA/176","PMD_X":166700,"PMD_Y":140400,"PMD_Z":750,"PN_NAME_E":"Beer 'Azeez","GR_GOVERNA":"Jerusalem","LOC_NAME_E":"Al Jib","PT_POINT_T":"Spring"}},{"type":"Feature","id":209,"geometry":{"type":"Point","coordinates":[163450,145000]},"properties":{"FID":209,"PMD_CODE":"BA/177","PMD_X":163450,"PMD_Y":145000,"PMD_Z":760,"PN_NAME_E":"Beit Surik","GR_GOVERNA":"Ramallah","LOC_NAME_E":"Beit Surik","PT_POINT_T":"Spring"}},{"type":"Feature","id":210,"geometry":{"type":"Point","coordinates":[162500,141400]},"properties":{"FID":210,"PMD_CODE":"BA/178","PMD_X":162500,"PMD_Y":141400,"PMD_Z":525,"PN_NAME_E":"Beit Duqqu","GR_GOVERNA":"Jerusalem","LOC_NAME_E":"Beit Duqqu","PT_POINT_T":"Spring"}},{"type":"Feature","id":211,"geometry":{"type":"Point","coordinates":[182200,139500]},"properties":{"FID":211,"PMD_CODE":"BA/180","PMD_X":182200,"PMD_Y":139500,"PMD_Z":285,"PN_NAME_E":"Janan","GR_GOVERNA":"Jerusalem","LOC_NAME_E":"Qatanna","PT_POINT_T":"Spring"}},{"type":"Feature","id":212,"geometry":{"type":"Point","coordinates":[]},"properties":{"FID":212,"PMD_CODE":"BA/181","PMD_X":0,"PMD_Y":0,"PMD_Z":0,"PN_NAME_E":"Al Balad","GR_GOVERNA":"Jerusalem","LOC_NAME_E":"Qatanna","PT_POINT_T":"Spring"}},{"type":"Feature","id":213,"geometry":{"type":"Point","coordinates":[163240,126080]},"properties":{"FID":213,"PMD_CODE":"BB/020","PMD_X":163240,"PMD_Y":126080,"PMD_Z":655,"PN_NAME_E":"Battir","GR_GOVERNA":"Bethlehem","LOC_NAME_E":"Battir","PT_POINT_T":"Spring"}},{"type":"Feature","id":214,"geometry":{"type":"Point","coordinates":[162590,125470]},"properties":{"FID":214,"PMD_CODE":"BB/021","PMD_X":162590,"PMD_Y":125470,"PMD_Z":630,"PN_NAME_E":"Al Jame'","GR_GOVERNA":"Bethlehem","LOC_NAME_E":"Battir","PT_POINT_T":"Spring"}},{"type":"Feature","id":215,"geometry":{"type":"Point","coordinates":[162200,124400]},"properties":{"FID":215,"PMD_CODE":"BB/022","PMD_X":162200,"PMD_Y":124400,"PMD_Z":710,"PN_NAME_E":"Al 'Amud","GR_GOVERNA":"Bethlehem","LOC_NAME_E":"Husan","PT_POINT_T":"Spring"}},{"type":"Feature","id":216,"geometry":{"type":"Point","coordinates":[162300,124350]},"properties":{"FID":216,"PMD_CODE":"BB/023","PMD_X":162300,"PMD_Y":124350,"PMD_Z":0,"PN_NAME_E":"Al Skhunah","GR_GOVERNA":"Bethlehem","LOC_NAME_E":"Husan","PT_POINT_T":"Spring"}},{"type":"Feature","id":217,"geometry":{"type":"Point","coordinates":[162600,124900]},"properties":{"FID":217,"PMD_CODE":"BB/024","PMD_X":162600,"PMD_Y":124900,"PMD_Z":150,"PN_NAME_E":"'Udah","GR_GOVERNA":"Bethlehem","LOC_NAME_E":"Husan","PT_POINT_T":"Spring"}},{"type":"Feature","id":218,"geometry":{"type":"Point","coordinates":[162800,124300]},"properties":{"FID":218,"PMD_CODE":"BB/025","PMD_X":162800,"PMD_Y":124300,"PMD_Z":0,"PN_NAME_E":"Berkat El Orof","GR_GOVERNA":"Bethlehem","LOC_NAME_E":"Husan","PT_POINT_T":"Spring"}},{"type":"Feature","id":219,"geometry":{"type":"Point","coordinates":[160800,124800]},"properties":{"FID":219,"PMD_CODE":"BB/026","PMD_X":160800,"PMD_Y":124800,"PMD_Z":675,"PN_NAME_E":"Al Kareesah","GR_GOVERNA":"Bethlehem","LOC_NAME_E":"Husan","PT_POINT_T":"Spring"}},{"type":"Feature","id":220,"geometry":{"type":"Point","coordinates":[162200,124350]},"properties":{"FID":220,"PMD_CODE":"BB/027","PMD_X":162200,"PMD_Y":124350,"PMD_Z":0,"PN_NAME_E":"Al Namus","GR_GOVERNA":"Bethlehem","LOC_NAME_E":"Husan","PT_POINT_T":"Spring"}},{"type":"Feature","id":221,"geometry":{"type":"Point","coordinates":[161150,121800]},"properties":{"FID":221,"PMD_CODE":"BB/028","PMD_X":161150,"PMD_Y":121800,"PMD_Z":610,"PN_NAME_E":"Al Balad","GR_GOVERNA":"Bethlehem","LOC_NAME_E":"Nahhalin","PT_POINT_T":"Spring"}},{"type":"Feature","id":222,"geometry":{"type":"Point","coordinates":[159500,122050]},"properties":{"FID":222,"PMD_CODE":"BB/029","PMD_X":159500,"PMD_Y":122050,"PMD_Z":0,"PN_NAME_E":"Fares","GR_GOVERNA":"Bethlehem","LOC_NAME_E":"Nahhalin","PT_POINT_T":"Spring"}},{"type":"Feature","id":223,"geometry":{"type":"Point","coordinates":[159890,123770]},"properties":{"FID":223,"PMD_CODE":"BB/030","PMD_X":159890,"PMD_Y":123770,"PMD_Z":630,"PN_NAME_E":"Fukin Al Balad","GR_GOVERNA":"Bethlehem","LOC_NAME_E":"Wadi Fukin","PT_POINT_T":"Spring"}},{"type":"Feature","id":224,"geometry":{"type":"Point","coordinates":[159940,123760]},"properties":{"FID":224,"PMD_CODE":"BB/031","PMD_X":159940,"PMD_Y":123760,"PMD_Z":650,"PN_NAME_E":"Al Magharah","GR_GOVERNA":"Bethlehem","LOC_NAME_E":"Wadi Fukin","PT_POINT_T":"Spring"}},{"type":"Feature","id":225,"geometry":{"type":"Point","coordinates":[159900,123800]},"properties":{"FID":225,"PMD_CODE":"BB/032","PMD_X":159900,"PMD_Y":123800,"PMD_Z":630,"PN_NAME_E":"Al Jurah","GR_GOVERNA":"Bethlehem","LOC_NAME_E":"Wadi Fukin","PT_POINT_T":"Spring"}},{"type":"Feature","id":226,"geometry":{"type":"Point","coordinates":[158800,121000]},"properties":{"FID":226,"PMD_CODE":"BB/033","PMD_X":158800,"PMD_Y":121000,"PMD_Z":590,"PN_NAME_E":"Suba","GR_GOVERNA":"Bethlehem","LOC_NAME_E":"Wadi Fukin","PT_POINT_T":"Spring"}},{"type":"Feature","id":227,"geometry":{"type":"Point","coordinates":[159800,123750]},"properties":{"FID":227,"PMD_CODE":"BB/034","PMD_X":159800,"PMD_Y":123750,"PMD_Z":620,"PN_NAME_E":"Sadeeq","GR_GOVERNA":"Bethlehem","LOC_NAME_E":"Wadi Fukin","PT_POINT_T":"Spring"}},{"type":"Feature","id":228,"geometry":{"type":"Point","coordinates":[159200,123000]},"properties":{"FID":228,"PMD_CODE":"BB/035","PMD_X":159200,"PMD_Y":123000,"PMD_Z":625,"PN_NAME_E":"Al Teen","GR_GOVERNA":"Bethlehem","LOC_NAME_E":"Wadi Fukin","PT_POINT_T":"Spring"}},{"type":"Feature","id":229,"geometry":{"type":"Point","coordinates":[159000,122900]},"properties":{"FID":229,"PMD_CODE":"BB/036","PMD_X":159000,"PMD_Y":122900,"PMD_Z":580,"PN_NAME_E":"Al Fawwar","GR_GOVERNA":"Bethlehem","LOC_NAME_E":"Wadi Fukin","PT_POINT_T":"Spring"}},{"type":"Feature","id":230,"geometry":{"type":"Point","coordinates":[159400,123300]},"properties":{"FID":230,"PMD_CODE":"BB/037","PMD_X":159400,"PMD_Y":123300,"PMD_Z":625,"PN_NAME_E":"Um Al Deek","GR_GOVERNA":"Bethlehem","LOC_NAME_E":"Wadi Fukin","PT_POINT_T":"Spring"}},{"type":"Feature","id":231,"geometry":{"type":"Point","coordinates":[158800,118700]},"properties":{"FID":231,"PMD_CODE":"BB/038","PMD_X":158800,"PMD_Y":118700,"PMD_Z":875,"PN_NAME_E":"Al Balad","GR_GOVERNA":"Bethlehem","LOC_NAME_E":"Hujayleh","PT_POINT_T":"Spring"}},{"type":"Feature","id":232,"geometry":{"type":"Point","coordinates":[164700,114100]},"properties":{"FID":232,"PMD_CODE":"BB/050","PMD_X":164700,"PMD_Y":114100,"PMD_Z":780,"PN_NAME_E":"Jala No 1","GR_GOVERNA":"Hebron","LOC_NAME_E":"Jala","PT_POINT_T":"Spring"}},{"type":"Feature","id":233,"geometry":{"type":"Point","coordinates":[164700,114100]},"properties":{"FID":233,"PMD_CODE":"BB/050A","PMD_X":164700,"PMD_Y":114100,"PMD_Z":780,"PN_NAME_E":"Jala No 2","GR_GOVERNA":"Hebron","LOC_NAME_E":"Jala","PT_POINT_T":"Spring"}},{"type":"Feature","id":234,"geometry":{"type":"Point","coordinates":[159400,114100]},"properties":{"FID":234,"PMD_CODE":"BB/051","PMD_X":159400,"PMD_Y":114100,"PMD_Z":900,"PN_NAME_E":"Muqattam","GR_GOVERNA":"Hebron","LOC_NAME_E":"Beit Ummar","PT_POINT_T":"Spring"}},{"type":"Feature","id":235,"geometry":{"type":"Point","coordinates":[158400,116000]},"properties":{"FID":235,"PMD_CODE":"BB/052","PMD_X":158400,"PMD_Y":116000,"PMD_Z":800,"PN_NAME_E":"Kasih","GR_GOVERNA":"Hebron","LOC_NAME_E":"Beit Ummar","PT_POINT_T":"Spring"}},{"type":"Feature","id":236,"geometry":{"type":"Point","coordinates":[158900,116000]},"properties":{"FID":236,"PMD_CODE":"BB/053","PMD_X":158900,"PMD_Y":116000,"PMD_Z":840,"PN_NAME_E":"Jadur","GR_GOVERNA":"Hebron","LOC_NAME_E":"Beit Ummar","PT_POINT_T":"Spring"}},{"type":"Feature","id":237,"geometry":{"type":"Point","coordinates":[159200,116600]},"properties":{"FID":237,"PMD_CODE":"BB/054","PMD_X":159200,"PMD_Y":116600,"PMD_Z":900,"PN_NAME_E":"Janan","GR_GOVERNA":"Hebron","LOC_NAME_E":"Beit Ummar","PT_POINT_T":"Spring"}},{"type":"Feature","id":238,"geometry":{"type":"Point","coordinates":[157500,112600]},"properties":{"FID":238,"PMD_CODE":"BB/059","PMD_X":157500,"PMD_Y":112600,"PMD_Z":850,"PN_NAME_E":"Baqqar","GR_GOVERNA":"Hebron","LOC_NAME_E":"Halhul","PT_POINT_T":"Spring"}},{"type":"Feature","id":239,"geometry":{"type":"Point","coordinates":[156900,111900]},"properties":{"FID":239,"PMD_CODE":"BB/060","PMD_X":156900,"PMD_Y":111900,"PMD_Z":835,"PN_NAME_E":"Qusbar","GR_GOVERNA":"Hebron","LOC_NAME_E":"Halhul","PT_POINT_T":"Spring"}},{"type":"Feature","id":240,"geometry":{"type":"Point","coordinates":[155300,111700]},"properties":{"FID":240,"PMD_CODE":"BB/061","PMD_X":155300,"PMD_Y":111700,"PMD_Z":725,"PN_NAME_E":"Al I'wainat","GR_GOVERNA":"Hebron","LOC_NAME_E":"Halhul","PT_POINT_T":"Spring"}},{"type":"Feature","id":241,"geometry":{"type":"Point","coordinates":[159600,110250]},"properties":{"FID":241,"PMD_CODE":"BB/062","PMD_X":159600,"PMD_Y":110250,"PMD_Z":880,"PN_NAME_E":"Al Teenah","GR_GOVERNA":"Hebron","LOC_NAME_E":"Halhul","PT_POINT_T":"Spring"}},{"type":"Feature","id":242,"geometry":{"type":"Point","coordinates":[158700,110200]},"properties":{"FID":242,"PMD_CODE":"BB/063","PMD_X":158700,"PMD_Y":110200,"PMD_Z":950,"PN_NAME_E":"Zabud","GR_GOVERNA":"Hebron","LOC_NAME_E":"Halhul","PT_POINT_T":"Spring"}},{"type":"Feature","id":243,"geometry":{"type":"Point","coordinates":[158200,109900]},"properties":{"FID":243,"PMD_CODE":"BB/064","PMD_X":158200,"PMD_Y":109900,"PMD_Z":950,"PN_NAME_E":"'Isa","GR_GOVERNA":"Hebron","LOC_NAME_E":"Halhul","PT_POINT_T":"Spring"}},{"type":"Feature","id":244,"geometry":{"type":"Point","coordinates":[159200,108900]},"properties":{"FID":244,"PMD_CODE":"BB/065","PMD_X":159200,"PMD_Y":108900,"PMD_Z":950,"PN_NAME_E":"Um Jabeir","GR_GOVERNA":"Hebron","LOC_NAME_E":"Halhul","PT_POINT_T":"Spring"}},{"type":"Feature","id":245,"geometry":{"type":"Point","coordinates":[158650,108130]},"properties":{"FID":245,"PMD_CODE":"BB/066","PMD_X":158650,"PMD_Y":108130,"PMD_Z":890,"PN_NAME_E":"Haskah","GR_GOVERNA":"Hebron","LOC_NAME_E":"Halhul","PT_POINT_T":"Spring"}},{"type":"Feature","id":246,"geometry":{"type":"Point","coordinates":[158200,108800]},"properties":{"FID":246,"PMD_CODE":"BB/067","PMD_X":158200,"PMD_Y":108800,"PMD_Z":600,"PN_NAME_E":"Beit Kahil","GR_GOVERNA":"Hebron","LOC_NAME_E":"Beit Kahil","PT_POINT_T":"Spring"}},{"type":"Feature","id":247,"geometry":{"type":"Point","coordinates":[154400,109000]},"properties":{"FID":247,"PMD_CODE":"BB/068","PMD_X":154400,"PMD_Y":109000,"PMD_Z":570,"PN_NAME_E":"Quf El Sharqia","GR_GOVERNA":"Hebron","LOC_NAME_E":"Beit Kahil","PT_POINT_T":"Spring"}},{"type":"Feature","id":248,"geometry":{"type":"Point","coordinates":[154400,109500]},"properties":{"FID":248,"PMD_CODE":"BB/069","PMD_X":154400,"PMD_Y":109500,"PMD_Z":560,"PN_NAME_E":"Quf West","GR_GOVERNA":"Hebron","LOC_NAME_E":"Beit Kahil","PT_POINT_T":"Spring"}},{"type":"Feature","id":249,"geometry":{"type":"Point","coordinates":[159450,105100]},"properties":{"FID":249,"PMD_CODE":"BB/070","PMD_X":159450,"PMD_Y":105100,"PMD_Z":860,"PN_NAME_E":"Deir Bahhah","GR_GOVERNA":"Hebron","LOC_NAME_E":"Hebron (Al Khalil)","PT_POINT_T":"Spring"}},{"type":"Feature","id":250,"geometry":{"type":"Point","coordinates":[153800,106400]},"properties":{"FID":250,"PMD_CODE":"BB/071","PMD_X":153800,"PMD_Y":106400,"PMD_Z":620,"PN_NAME_E":"Bustan","GR_GOVERNA":"Hebron","LOC_NAME_E":"Taffuh","PT_POINT_T":"Spring"}},{"type":"Feature","id":251,"geometry":{"type":"Point","coordinates":[156900,101950]},"properties":{"FID":251,"PMD_CODE":"BB/072","PMD_X":156900,"PMD_Y":101950,"PMD_Z":0,"PN_NAME_E":"Unqor","GR_GOVERNA":"Hebron","LOC_NAME_E":"Dura","PT_POINT_T":"Spring"}},{"type":"Feature","id":252,"geometry":{"type":"Point","coordinates":[156600,101800]},"properties":{"FID":252,"PMD_CODE":"BB/073","PMD_X":156600,"PMD_Y":101800,"PMD_Z":815,"PN_NAME_E":"Tayyur","GR_GOVERNA":"Hebron","LOC_NAME_E":"Dura","PT_POINT_T":"Spring"}},{"type":"Feature","id":253,"geometry":{"type":"Point","coordinates":[153300,104300]},"properties":{"FID":253,"PMD_CODE":"BB/074","PMD_X":153300,"PMD_Y":104300,"PMD_Z":600,"PN_NAME_E":"Al Sa'biyyah","GR_GOVERNA":"Hebron","LOC_NAME_E":"Dura","PT_POINT_T":"Spring"}},{"type":"Feature","id":254,"geometry":{"type":"Point","coordinates":[154000,104600]},"properties":{"FID":254,"PMD_CODE":"BB/075","PMD_X":154000,"PMD_Y":104600,"PMD_Z":630,"PN_NAME_E":"Al Ma'mudiyyah","GR_GOVERNA":"Hebron","LOC_NAME_E":"Dura","PT_POINT_T":"Spring"}},{"type":"Feature","id":255,"geometry":{"type":"Point","coordinates":[151600,106000]},"properties":{"FID":255,"PMD_CODE":"BB/076","PMD_X":151600,"PMD_Y":106000,"PMD_Z":530,"PN_NAME_E":"Fir'a","GR_GOVERNA":"Hebron","LOC_NAME_E":"Dura","PT_POINT_T":"Spring"}},{"type":"Feature","id":256,"geometry":{"type":"Point","coordinates":[154900,101500]},"properties":{"FID":256,"PMD_CODE":"BB/077","PMD_X":154900,"PMD_Y":101500,"PMD_Z":810,"PN_NAME_E":"Kanar Al Gharbiyyah","GR_GOVERNA":"Hebron","LOC_NAME_E":"Dura","PT_POINT_T":"Spring"}},{"type":"Feature","id":257,"geometry":{"type":"Point","coordinates":[154900,101500]},"properties":{"FID":257,"PMD_CODE":"BB/077A","PMD_X":154900,"PMD_Y":101500,"PMD_Z":0,"PN_NAME_E":"Kanar Al Sharqiyyah","GR_GOVERNA":"Hebron","LOC_NAME_E":"Dura","PT_POINT_T":"Spring"}},{"type":"Feature","id":258,"geometry":{"type":"Point","coordinates":[155200,101600]},"properties":{"FID":258,"PMD_CODE":"BB/077B","PMD_X":155200,"PMD_Y":101600,"PMD_Z":825,"PN_NAME_E":"Kanar Wusta","GR_GOVERNA":"Hebron","LOC_NAME_E":"Dura","PT_POINT_T":"Spring"}},{"type":"Feature","id":259,"geometry":{"type":"Point","coordinates":[154900,101600]},"properties":{"FID":259,"PMD_CODE":"BB/078","PMD_X":154900,"PMD_Y":101600,"PMD_Z":825,"PN_NAME_E":"Sha'ban","GR_GOVERNA":"Hebron","LOC_NAME_E":"Dura","PT_POINT_T":"Spring"}},{"type":"Feature","id":260,"geometry":{"type":"Point","coordinates":[152200,102700]},"properties":{"FID":260,"PMD_CODE":"BB/079","PMD_X":152200,"PMD_Y":102700,"PMD_Z":800,"PN_NAME_E":"Set Al Rum","GR_GOVERNA":"Hebron","LOC_NAME_E":"Dura","PT_POINT_T":"Spring"}},{"type":"Feature","id":261,"geometry":{"type":"Point","coordinates":[151600,100000]},"properties":{"FID":261,"PMD_CODE":"BB/080","PMD_X":151600,"PMD_Y":100000,"PMD_Z":613,"PN_NAME_E":"Kallat Dyab","GR_GOVERNA":"Hebron","LOC_NAME_E":"Dura","PT_POINT_T":"Spring"}},{"type":"Feature","id":262,"geometry":{"type":"Point","coordinates":[152900,100000]},"properties":{"FID":262,"PMD_CODE":"BB/081","PMD_X":152900,"PMD_Y":100000,"PMD_Z":850,"PN_NAME_E":"Al Fraidees","GR_GOVERNA":"Hebron","LOC_NAME_E":"Dura","PT_POINT_T":"Spring"}},{"type":"Feature","id":263,"geometry":{"type":"Point","coordinates":[152900,100500]},"properties":{"FID":263,"PMD_CODE":"BB/082","PMD_X":152900,"PMD_Y":100500,"PMD_Z":870,"PN_NAME_E":"Junaynah","GR_GOVERNA":"Hebron","LOC_NAME_E":"Dura","PT_POINT_T":"Spring"}},{"type":"Feature","id":264,"geometry":{"type":"Point","coordinates":[154700,100250]},"properties":{"FID":264,"PMD_CODE":"BB/083","PMD_X":154700,"PMD_Y":100250,"PMD_Z":790,"PN_NAME_E":"'Imran  No. 2","GR_GOVERNA":"Hebron","LOC_NAME_E":"Dura","PT_POINT_T":"Spring"}},{"type":"Feature","id":265,"geometry":{"type":"Point","coordinates":[154650,100350]},"properties":{"FID":265,"PMD_CODE":"BB/083A","PMD_X":154650,"PMD_Y":100350,"PMD_Z":790,"PN_NAME_E":"'Imran  No. 1","GR_GOVERNA":"Hebron","LOC_NAME_E":"Dura","PT_POINT_T":"Spring"}},{"type":"Feature","id":266,"geometry":{"type":"Point","coordinates":[154550,100250]},"properties":{"FID":266,"PMD_CODE":"BB/084","PMD_X":154550,"PMD_Y":100250,"PMD_Z":825,"PN_NAME_E":"Abu Khait","GR_GOVERNA":"Hebron","LOC_NAME_E":"Dura","PT_POINT_T":"Spring"}},{"type":"Feature","id":267,"geometry":{"type":"Point","coordinates":[156000,100000]},"properties":{"FID":267,"PMD_CODE":"BB/085","PMD_X":156000,"PMD_Y":100000,"PMD_Z":780,"PN_NAME_E":"Al Hejrah","GR_GOVERNA":"Hebron","LOC_NAME_E":"Dura","PT_POINT_T":"Spring"}},{"type":"Feature","id":268,"geometry":{"type":"Point","coordinates":[154860,99140]},"properties":{"FID":268,"PMD_CODE":"BB/086","PMD_X":154860,"PMD_Y":99140,"PMD_Z":770,"PN_NAME_E":"Delbah","GR_GOVERNA":"Hebron","LOC_NAME_E":"Dura","PT_POINT_T":"Spring"}},{"type":"Feature","id":269,"geometry":{"type":"Point","coordinates":[154300,100000]},"properties":{"FID":269,"PMD_CODE":"BB/087","PMD_X":154300,"PMD_Y":100000,"PMD_Z":900,"PN_NAME_E":"Al Majnunah","GR_GOVERNA":"Hebron","LOC_NAME_E":"Dura","PT_POINT_T":"Spring"}},{"type":"Feature","id":270,"geometry":{"type":"Point","coordinates":[192400,124900]},"properties":{"FID":270,"PMD_CODE":"CB/020","PMD_X":192400,"PMD_Y":124900,"PMD_Z":390,"PN_NAME_E":"Fashkhah Group","GR_GOVERNA":"Bethlehem","LOC_NAME_E":"Dead Sea","PT_POINT_T":"Spring"}},{"type":"Feature","id":271,"geometry":{"type":"Point","coordinates":[193210,125930]},"properties":{"FID":271,"PMD_CODE":"CB/020A","PMD_X":193210,"PMD_Y":125930,"PMD_Z":0,"PN_NAME_E":"Ghazal","GR_GOVERNA":"Jericho","LOC_NAME_E":"Dead Sea","PT_POINT_T":"Spring"}},{"type":"Feature","id":272,"geometry":{"type":"Point","coordinates":[192940,125470]},"properties":{"FID":272,"PMD_CODE":"CB/020B","PMD_X":192940,"PMD_Y":125470,"PMD_Z":0,"PN_NAME_E":"Tannur","GR_GOVERNA":"Bethlehem","LOC_NAME_E":"Dead Sea","PT_POINT_T":"Spring"}},{"type":"Feature","id":273,"geometry":{"type":"Point","coordinates":[189000,114800]},"properties":{"FID":273,"PMD_CODE":"CB/021","PMD_X":189000,"PMD_Y":114800,"PMD_Z":390,"PN_NAME_E":"Ghwair","GR_GOVERNA":"Jericho","LOC_NAME_E":"Dead Sea","PT_POINT_T":"Spring"}},{"type":"Feature","id":274,"geometry":{"type":"Point","coordinates":[]},"properties":{"FID":274,"PMD_CODE":"CB/021A","PMD_X":0,"PMD_Y":0,"PMD_Z":0,"PN_NAME_E":"Ghazal South","GR_GOVERNA":"Jericho","LOC_NAME_E":"Dead Sea","PT_POINT_T":"Spring"}},{"type":"Feature","id":275,"geometry":{"type":"Point","coordinates":[188800,112800]},"properties":{"FID":275,"PMD_CODE":"CB/022","PMD_X":188800,"PMD_Y":112800,"PMD_Z":390,"PN_NAME_E":"Turba","GR_GOVERNA":"Jericho","LOC_NAME_E":"Dead Sea","PT_POINT_T":"Spring"}},{"type":"Feature","id":276,"geometry":{"type":"Point","coordinates":[172500,131160]},"properties":{"FID":276,"PMD_CODE":"CB/025","PMD_X":172500,"PMD_Y":131160,"PMD_Z":650,"PN_NAME_E":"Um Al Daraj","GR_GOVERNA":"Jerusalem","LOC_NAME_E":"Selwan","PT_POINT_T":"Spring"}},{"type":"Feature","id":277,"geometry":{"type":"Point","coordinates":[167600,121700]},"properties":{"FID":277,"PMD_CODE":"CB/030","PMD_X":167600,"PMD_Y":121700,"PMD_Z":725,"PN_NAME_E":"Irtas","GR_GOVERNA":"Bethlehem","LOC_NAME_E":"Artas","PT_POINT_T":"Spring"}},{"type":"Feature","id":278,"geometry":{"type":"Point","coordinates":[166480,121550]},"properties":{"FID":278,"PMD_CODE":"CB/031","PMD_X":166480,"PMD_Y":121550,"PMD_Z":775,"PN_NAME_E":"'Itan","GR_GOVERNA":"Bethlehem","LOC_NAME_E":"Artas","PT_POINT_T":"Spring"}},{"type":"Feature","id":279,"geometry":{"type":"Point","coordinates":[166700,121800]},"properties":{"FID":279,"PMD_CODE":"CB/031A","PMD_X":166700,"PMD_Y":121800,"PMD_Z":800,"PN_NAME_E":"Al Farrujah","GR_GOVERNA":"Bethlehem","LOC_NAME_E":"Artas","PT_POINT_T":"Spring"}},{"type":"Feature","id":280,"geometry":{"type":"Point","coordinates":[165900,121000]},"properties":{"FID":280,"PMD_CODE":"CB/032","PMD_X":165900,"PMD_Y":121000,"PMD_Z":0,"PN_NAME_E":"Saleh","GR_GOVERNA":"Bethlehem","LOC_NAME_E":"Artas","PT_POINT_T":"Spring"}},{"type":"Feature","id":281,"geometry":{"type":"Point","coordinates":[167600,121600]},"properties":{"FID":281,"PMD_CODE":"CB/033A","PMD_X":167600,"PMD_Y":121600,"PMD_Z":0,"PN_NAME_E":"Wadi Al Biyar","GR_GOVERNA":"Bethlehem","LOC_NAME_E":"Artas","PT_POINT_T":"Spring"}},{"type":"Feature","id":282,"geometry":{"type":"Point","coordinates":[161000,115900]},"properties":{"FID":282,"PMD_CODE":"CB/040","PMD_X":161000,"PMD_Y":115900,"PMD_Z":900,"PN_NAME_E":"Mareena","GR_GOVERNA":"Hebron","LOC_NAME_E":"Beit Ummar","PT_POINT_T":"Spring"}},{"type":"Feature","id":283,"geometry":{"type":"Point","coordinates":[161100,114600]},"properties":{"FID":283,"PMD_CODE":"CB/041","PMD_X":161100,"PMD_Y":114600,"PMD_Z":910,"PN_NAME_E":"Kufeen","GR_GOVERNA":"Hebron","LOC_NAME_E":"Beit Ummar","PT_POINT_T":"Spring"}},{"type":"Feature","id":284,"geometry":{"type":"Point","coordinates":[163200,114200]},"properties":{"FID":284,"PMD_CODE":"CB/042","PMD_X":163200,"PMD_Y":114200,"PMD_Z":825,"PN_NAME_E":"Beer 'Id","GR_GOVERNA":"Hebron","LOC_NAME_E":"Al'Arrub Camp","PT_POINT_T":"Spring"}},{"type":"Feature","id":285,"geometry":{"type":"Point","coordinates":[163200,114300]},"properties":{"FID":285,"PMD_CODE":"CB/043","PMD_X":163200,"PMD_Y":114300,"PMD_Z":825,"PN_NAME_E":"Beer Hamed","GR_GOVERNA":"Hebron","LOC_NAME_E":"Al'Arrub Camp","PT_POINT_T":"Spring"}},{"type":"Feature","id":286,"geometry":{"type":"Point","coordinates":[164100,114000]},"properties":{"FID":286,"PMD_CODE":"CB/044","PMD_X":164100,"PMD_Y":114000,"PMD_Z":950,"PN_NAME_E":"Al Marj","GR_GOVERNA":"Hebron","LOC_NAME_E":"Al'Arrub Camp","PT_POINT_T":"Spring"}},{"type":"Feature","id":287,"geometry":{"type":"Point","coordinates":[163600,114400]},"properties":{"FID":287,"PMD_CODE":"CB/045","PMD_X":163600,"PMD_Y":114400,"PMD_Z":820,"PN_NAME_E":"Harhash","GR_GOVERNA":"Hebron","LOC_NAME_E":"Al'Arrub Camp","PT_POINT_T":"Spring"}},{"type":"Feature","id":288,"geometry":{"type":"Point","coordinates":[163520,114220]},"properties":{"FID":288,"PMD_CODE":"CB/046","PMD_X":163520,"PMD_Y":114220,"PMD_Z":0,"PN_NAME_E":"Barrada","GR_GOVERNA":"Hebron","LOC_NAME_E":"Al'Arrub Camp","PT_POINT_T":"Spring"}},{"type":"Feature","id":289,"geometry":{"type":"Point","coordinates":[163100,113600]},"properties":{"FID":289,"PMD_CODE":"CB/047A","PMD_X":163100,"PMD_Y":113600,"PMD_Z":0,"PN_NAME_E":"Beer Al Bas","GR_GOVERNA":"Hebron","LOC_NAME_E":"Al'Arrub Camp","PT_POINT_T":"Spring"}},{"type":"Feature","id":290,"geometry":{"type":"Point","coordinates":[162900,112000]},"properties":{"FID":290,"PMD_CODE":"CB/047B","PMD_X":162900,"PMD_Y":112000,"PMD_Z":860,"PN_NAME_E":"Ein Al Bas","GR_GOVERNA":"Hebron","LOC_NAME_E":"Al'Arrub Camp","PT_POINT_T":"Spring"}},{"type":"Feature","id":291,"geometry":{"type":"Point","coordinates":[164000,114300]},"properties":{"FID":291,"PMD_CODE":"CB/048","PMD_X":164000,"PMD_Y":114300,"PMD_Z":850,"PN_NAME_E":"Beer 'Ayyad","GR_GOVERNA":"Hebron","LOC_NAME_E":"Al'Arrub Camp","PT_POINT_T":"Spring"}},{"type":"Feature","id":292,"geometry":{"type":"Point","coordinates":[164500,112600]},"properties":{"FID":292,"PMD_CODE":"CB/050","PMD_X":164500,"PMD_Y":112600,"PMD_Z":825,"PN_NAME_E":"Kuweiziba","GR_GOVERNA":"Hebron","LOC_NAME_E":"Sa'ir","PT_POINT_T":"Spring"}},{"type":"Feature","id":293,"geometry":{"type":"Point","coordinates":[163700,110250]},"properties":{"FID":293,"PMD_CODE":"CB/051","PMD_X":163700,"PMD_Y":110250,"PMD_Z":860,"PN_NAME_E":"Sa'ir","GR_GOVERNA":"Hebron","LOC_NAME_E":"Sa'ir","PT_POINT_T":"Spring"}},{"type":"Feature","id":294,"geometry":{"type":"Point","coordinates":[159750,110450]},"properties":{"FID":294,"PMD_CODE":"CB/052","PMD_X":159750,"PMD_Y":110450,"PMD_Z":935,"PN_NAME_E":"Therweh","GR_GOVERNA":"Hebron","LOC_NAME_E":"Halhul","PT_POINT_T":"Spring"}},{"type":"Feature","id":295,"geometry":{"type":"Point","coordinates":[163000,92600]},"properties":{"FID":295,"PMD_CODE":"CB/055","PMD_X":163000,"PMD_Y":92600,"PMD_Z":800,"PN_NAME_E":"Al Karmel","GR_GOVERNA":"Hebron","LOC_NAME_E":"Yatta","PT_POINT_T":"Spring"}},{"type":"Feature","id":296,"geometry":{"type":"Point","coordinates":[165000,91300]},"properties":{"FID":296,"PMD_CODE":"CB/056","PMD_X":165000,"PMD_Y":91300,"PMD_Z":800,"PN_NAME_E":"Al Tawani","GR_GOVERNA":"Hebron","LOC_NAME_E":"Yatta","PT_POINT_T":"Spring"}},{"type":"Feature","id":297,"geometry":{"type":"Point","coordinates":[]},"properties":{"FID":297,"PMD_CODE":"NS/001","PMD_X":0,"PMD_Y":0,"PMD_Z":0,"PN_NAME_E":"Yanbou'","GR_GOVERNA":"Salfit","LOC_NAME_E":"Salfit","PT_POINT_T":"Spring"}},{"type":"Feature","id":298,"geometry":{"type":"Point","coordinates":[]},"properties":{"FID":298,"PMD_CODE":"NS/002","PMD_X":0,"PMD_Y":0,"PMD_Z":0,"PN_NAME_E":"Al Balad","GR_GOVERNA":"Nablus","LOC_NAME_E":"Beit Iba","PT_POINT_T":"Spring"}},{"type":"Feature","id":299,"geometry":{"type":"Point","coordinates":[]},"properties":{"FID":299,"PMD_CODE":"NS/003","PMD_X":0,"PMD_Y":0,"PMD_Z":0,"PN_NAME_E":"Qasabeh","GR_GOVERNA":"Nablus","LOC_NAME_E":"Qabalan","PT_POINT_T":"Spring"}},{"type":"Feature","id":300,"geometry":{"type":"Point","coordinates":[]},"properties":{"FID":300,"PMD_CODE":"NS/004","PMD_X":0,"PMD_Y":0,"PMD_Z":0,"PN_NAME_E":"Al Saqi","GR_GOVERNA":"Ramallah","LOC_NAME_E":"Bir Zeit","PT_POINT_T":"Spring"}},{"type":"Feature","id":301,"geometry":{"type":"Point","coordinates":[]},"properties":{"FID":301,"PMD_CODE":"NS/005","PMD_X":0,"PMD_Y":0,"PMD_Z":0,"PN_NAME_E":"Qusra","GR_GOVERNA":"Nablus","LOC_NAME_E":"Qusra","PT_POINT_T":"Spring"}},{"type":"Feature","id":302,"geometry":{"type":"Point","coordinates":[]},"properties":{"FID":302,"PMD_CODE":"NS/006","PMD_X":0,"PMD_Y":0,"PMD_Z":0,"PN_NAME_E":"Al Sharqiyyah","GR_GOVERNA":"Nablus","LOC_NAME_E":"Beit Iba","PT_POINT_T":"Spring"}}]
}